Workbook

Sheet RESUMEN
B2: IMPORTACIONES RUBI HA ABRIL
B4: Customer Name | C4: Division | D4: Promotion No | E4: Promotion Name | F4: From | G4: To | H4: SPMS | I4: Cálculo LG | J4: Diferencia | K4: Retorno/Exceso
B5: IMPORTACIONES RUBI S.A. | C5: Cooking | D5: PR-NTSO-20240405-0031 | E5: 2024 - RUBI - Cooking - 20240410 AL 20240430 | F5: 20240410 | G5: 20240430 | H5: =SUMIF('CALCULATE (2)'!$D:$D,RESUMEN!$D5,'CALCULATE (2)'!$BA:$BA) -> 5796.56 | I5: =SUMIF('CALCULATE (2)'!$D:$D,RESUMEN!$D5,'CALCULATE (2)'!$V:$V) -> 5796.56 | J5: =+I5-H5 -> 0 | K5: =+IF(J5<=0,"Retorno","Exceso") -> Retorno
B6: IMPORTACIONES RUBI S.A. | C6: Cooking | D6: PR-NTSO-20240415-0011 | E6: 2024 - RUBI - Cooking - 20240420 AL 20240430 | F6: 20240420 | G6: 20240430 | H6: =SUMIF('CALCULATE (2)'!$D:$D,RESUMEN!$D6,'CALCULATE (2)'!$BA:$BA) -> 1601.67 | I6: =SUMIF('CALCULATE (2)'!$D:$D,RESUMEN!$D6,'CALCULATE (2)'!$V:$V) -> 0 | J6: =+I6-H6 -> -1601.67 | K6: =+IF(J6<=0,"Retorno","Exceso") -> Retorno
B7: IMPORTACIONES RUBI S.A. | C7: Cooking | D7: PR-NTSO-20240416-0005 | E7: 2024 - RUBI - Cooking - 20240422 AL 20240430 | F7: 20240422 | G7: 20240430 | H7: =SUMIF('CALCULATE (2)'!$D:$D,RESUMEN!$D7,'CALCULATE (2)'!$BA:$BA) -> 8313.9 | I7: =SUMIF('CALCULATE (2)'!$D:$D,RESUMEN!$D7,'CALCULATE (2)'!$V:$V) -> 7245.7 | J7: =+I7-H7 -> -1068.2 | K7: =+IF(J7<=0,"Retorno","Exceso") -> Retorno
B8: IMPORTACIONES RUBI S.A. | C8: W/M | D8: PR-NTSO-20240327-0059 | E8: 2024 - RUBI - W/M - 20240403 AL 20240430 | F8: 20240403 | G8: 20240430 | H8: =SUMIF('CALCULATE (2)'!$D:$D,RESUMEN!$D8,'CALCULATE (2)'!$BA:$BA) -> 24306.55 | I8: =SUMIF('CALCULATE (2)'!$D:$D,RESUMEN!$D8,'CALCULATE (2)'!$V:$V) -> 13175.08 | J8: =+I8-H8 -> -11131.47 | K8: =+IF(J8<=0,"Retorno","Exceso") -> Retorno
B9: IMPORTACIONES RUBI S.A. | C9: W/M | D9: PR-NTSO-20240416-0006 | E9: 2024 - RUBI - W/M - 20240422 AL 20240430 | F9: 20240422 | G9: 20240430 | H9: =SUMIF('CALCULATE (2)'!$D:$D,RESUMEN!$D9,'CALCULATE (2)'!$BA:$BA) -> 9695.6 | I9: =SUMIF('CALCULATE (2)'!$D:$D,RESUMEN!$D9,'CALCULATE (2)'!$V:$V) -> 4339.02 | J9: =+I9-H9 -> -5356.58 | K9: =+IF(J9<=0,"Retorno","Exceso") -> Retorno
G10: Total | H10: =+SUBTOTAL(9,H5:H9) -> 49714.28 | I10: =+SUBTOTAL(9,I5:I9) -> 30556.36 | J10: =+SUBTOTAL(9,J5:J9) -> -19157.92
J13: Variación | K13: Retorno/Exceso
G14: =C5 -> Cooking | H14: =SUMIF($C$5:$C$9,G14,$H$5:$H$9) -> 15712.13 | I14: =SUMIF($C$5:$C$9,G14,$I$5:$I$9) -> 13042.26 | J14: =+I14-H14 -> -2669.87 | K14: =+IF(J14<=0,"Retorno","Exceso") -> Retorno
G15: W/M | H15: =SUMIF($C$5:$C$9,G15,$H$5:$H$9) -> 34002.15 | I15: =SUMIF($C$5:$C$9,G15,$I$5:$I$9) -> 17514.1 | J15: =+I15-H15 -> -16488.05 | K15: =+IF(J15<=0,"Retorno","Exceso") -> Retorno
G16: REF | H16: =SUMIF($C$5:$C$9,G16,$H$5:$H$9) -> 0 | I16: =SUMIF($C$5:$C$9,G16,$I$5:$I$9) -> 0 | J16: =+I16-H16 -> 0 | K16: =+IF(J16<=0,"Retorno","Exceso") -> Retorno
H17: =SUM(H14:H16) -> 49714.28 | I17: =SUM(I14:I16) -> 30556.36 | J17: =SUM(J14:J16) -> -19157.92

Sheet Sheet1
A3: Sum of Monto Total (Book)
A4: Customer Name | B4: Division Name | C4: Promotion No | D4: Promotion Name | E4: Fecha Inicio | F4: Fecha Fin | G4: Total
A5: IMPORTACIONES RUBI S.A. | B5: Cooking | C5: PR-NTSO-20240405-0031 | D5: 2024 - RUBI - Cooking - 20240410 AL 20240430 | E5: 20240410 | F5: 20240430 | G5: 5796.56
A6: IMPORTACIONES RUBI S.A. | B6: Cooking | C6: PR-NTSO-20240415-0011 | D6: 2024 - RUBI - Cooking - 20240420 AL 20240430 | E6: 20240420 | F6: 20240430 | G6: 0
A7: IMPORTACIONES RUBI S.A. | B7: Cooking | C7: PR-NTSO-20240416-0005 | D7: 2024 - RUBI - Cooking - 20240422 AL 20240430 | E7: 20240422 | F7: 20240430 | G7: 0
A8: IMPORTACIONES RUBI S.A. | B8: W/M | C8: PR-NTSO-20240327-0059 | D8: 2024 - RUBI - W/M - 20240403 AL 20240430 | E8: 20240403 | F8: 20240430 | G8: 13175.08
A9: IMPORTACIONES RUBI S.A. | B9: W/M | C9: PR-NTSO-20240416-0006 | D9: 2024 - RUBI - W/M - 20240422 AL 20240430 | E9: 20240422 | F9: 20240430 | G9: 4339.02
A10: Grand Total | G10: 23310.66

Sheet CALCULATE (2)
A1: Seq | B1: Company Name | C1: Division Name | D1: Promotion No | E1: Promotion Line No | F1: Fecha Inicio | G1: Fecha Fin | H1: Customer Code | I1: Modelo | J1: PVP | K1: Costo Sellin | L1: * Precio Promotion | M1: * Nuevo Margen | N1: * Costo Promocion | O1: Diferencia | P1: Unidades | Q1: * Regalo | R1: * Bundle Cost | S1: * Bundle Cost Rate | T1: Bundle Diff | U1: Bundle Unidades | V1: Monto Total (Book) | W1: Monto Total | X1: Mix Adjust Amount | Y1: * NOTE * | Z1: FCST UNIT AMT DIFF | AA1: FCST QTY DIFF | AB1: FCST AMT DIFF | AC1: * ALL / SHOP / WEB | AD1: ADDITIONAL_COND | AE1: Priority | AF1: Ref Line | AG1: Stock | AH1: Sellin in Promo | AI1: Sellout Qty | AJ1: Return Qty | AK1: Promo Applied Qty | AL1: Customer Qty | AM1: * Limit Qty | AN1: Control Over Stock | AO1: Control Not Applied | AP1: Control Cust Request | AQ1: Control Below Cost | AR1: Control Limit | AS1: Bundle Seq | AT1: Bundle Priority | AU1: Bundle Stock | AV1: Bundle Sellout | AW1: Same Model | AX1: Promotion Line Status Code | AY1: FCST Unit Amt | AZ1: FCST Qty | BA1: FCST Amt | BB1: FCST Amt(Book) | BC1: Actual Accu Qty | BD1: Actual Accu Amt | BE1: Customer Name | BF1: Promotion Name | BG1: Model Code | BH1: Currency | BI1: TC | BJ1: Line Remark | BK1: Concate
A2: 1 | B2: H&A Company | C2: Cooking | D2: PR-NTSO-20240405-0031 | E2: 1 | F2: 20240410 | G2: 20240430 | H2: PE000820001B | I2: RSG314M.FSTGLPR | J2: 0 | K2: 1944.15 | L2: 1599 | M2: 10 | N2: 1219.58 | O2: 724.57 | P2: 8 | Q2: 0 | S2: 0 | V2: 5796.56 | Z2: 0 | AA2: 0 | AB2: 0 | AC2: ALL | AE2: 1-BASIC | AG2: 18 | AH2: 0 | AI2: 18 | AJ2: 0 | AK2: 18 | AL2: 0 | AM2: 8 | AN2: 0 | AO2: 0 | AP2: 0 | AQ2: 0 | AR2: 10 | AX2: APPROVED | AY2: 724.57 | AZ2: 8 | BA2: 5796.56 | BB2: 5796.56 | BC2: 0 | BD2: 0 | BE2: IMPORTACIONES RUBI S.A. | BF2: 2024 - RUBI - Cooking - 20240410 AL 20240430 | BG2: RSG314M.FSTGLPR | BH2: PEN | BI2: 1 | BJ2: 1599_10__8 | BK2: PR-NTSO-20240405-0031RSG314M.FSTGLPR
A3: 2 | B3: H&A Company | C3: Cooking | D3: PR-NTSO-20240415-0011 | E3: 1 | F3: 20240420 | G3: 20240430 | H3: PE000820001B | I3: MS2596DIR.BBKGLPR | J3: 0 | K3: 365.34 | L3: 379 | M3: 10 | N3: 289.07 | O3: 76.27 | P3: 0 | Q3: 0 | S3: 0 | V3: 0 | Z3: 0 | AA3: -21 | AB3: -1601.67 | AC3: ALL | AE3: 1-BASIC | AG3: 24 | AH3: 0 | AI3: 0 | AJ3: 0 | AK3: 0 | AL3: 0 | AM3: 0 | AN3: 0 | AO3: 0 | AP3: 0 | AQ3: 0 | AR3: 0 | AX3: APPROVED | AY3: 76.27 | AZ3: 21 | BA3: 1601.67 | BB3: 1601.67 | BC3: 0 | BD3: 0 | BE3: IMPORTACIONES RUBI S.A. | BF3: 2024 - RUBI - Cooking - 20240420 AL 20240430 | BG3: MS2596DIR.BBKGLPR | BH3: PEN | BI3: 1 | BJ3: 379_10__ | BK3: PR-NTSO-20240415-0011MS2596DIR.BBKGLPR
A4: 3 | B4: H&A Company | C4: Cooking | D4: PR-NTSO-20240416-0005 | E4: 1 | F4: 20240422 | G4: 20240430 | H4: PE000820001B | I4: MS4296DIR.BBKGLPR | J4: 0 | K4: 433.98 | L4: 539 | M4: 10 | N4: 411.1 | O4: 22.88 | P4: 0 | Q4: 0 | S4: 0 | V4: 0 | Z4: 15.25 | AA4: -140 | AB4: -1068.2 | AC4: ALL | AE4: 1-BASIC | AG4: 49 | AH4: 0 | AI4: 0 | AJ4: 0 | AK4: 0 | AL4: 0 | AM4: 0 | AN4: 0 | AO4: 0 | AP4: 0 | AQ4: 0 | AR4: 0 | AX4: APPROVED | AY4: 7.63 | AZ4: 140 | BA4: 1068.2 | BB4: 1068.2 | BC4: 0 | BD4: 0 | BE4: IMPORTACIONES RUBI S.A. | BF4: 2024 - RUBI - Cooking - 20240422 AL 20240430 | BG4: MS4296DIR.BBKGLPR | BH4: PEN | BI4: 1 | BJ4: 539_10__ | BK4: PR-NTSO-20240416-0005MS4296DIR.BBKGLPR
A5: 4 | B5: H&A Company | C5: Cooking | D5: PR-NTSO-20240416-0005 | E5: 2 | F5: 20240422 | G5: 20240430 | H5: PE000820001B | I5: RSG314M.FSTGLPR | J5: 0 | K5: 1944.15 | L5: 1599 | M5: 10 | N5: 1219.58 | O5: 724.57 | P5: 10 | Q5: 0 | S5: 0 | V5: 7245.7 | Z5: 0 | AA5: 0 | AB5: 0 | AC5: ALL | AE5: 2-ADDITIONAL | AF5: 1 | AG5: 10 | AH5: 0 | AI5: 10 | AJ5: 0 | AK5: 10 | AL5: 0 | AM5: 0 | AN5: 0 | AO5: 0 | AP5: 0 | AQ5: 0 | AR5: 0 | AX5: APPROVED | AY5: 724.57 | AZ5: 10 | BA5: 7245.7 | BB5: 7245.7 | BC5: 0 | BD5: 0 | BE5: IMPORTACIONES RUBI S.A. | BF5: 2024 - RUBI - Cooking - 20240422 AL 20240430 | BG5: RSG314M.FSTGLPR | BH5: PEN | BI5: 1 | BJ5: 1599_10__ | BK5: PR-NTSO-20240416-0005RSG314M.FSTGLPR
A6: 5 | B6: H&A Company | C6: W/M | D6: PR-NTSO-20240327-0059 | E6: 1 | F6: 20240403 | G6: 20240430 | H6: PE000820001B | I6: WD12BVC2S6C.ABLGLGP | J6: 0 | K6: 2279.75 | L6: 2099 | M6: 10 | N6: 1600.93 | O6: 678.82 | P6: 5 | Q6: 0 | S6: 0 | V6: 3394.1 | Z6: 0 | AA6: -5 | AB6: -3394.1 | AC6: ALL | AE6: 1-BASIC | AG6: 36 | AH6: 0 | AI6: 5 | AJ6: 0 | AK6: 5 | AL6: 0 | AM6: 0 | AN6: 0 | AO6: 0 | AP6: 0 | AQ6: 0 | AR6: 0 | AX6: APPROVED | AY6: 678.82 | AZ6: 10 | BA6: 6788.2 | BB6: 6788.2 | BC6: 0 | BD6: 0 | BE6: IMPORTACIONES RUBI S.A. | BF6: 2024 - RUBI - W/M - 20240403 AL 20240430 | BG6: WD12BVC2S6C.ABLGLGP | BH6: PEN | BI6: 1 | BJ6: 2099_10__ | BK6: PR-NTSO-20240327-0059WD12BVC2S6C.ABLGLGP
A7: 6 | B7: H&A Company | C7: W/M | D7: PR-NTSO-20240327-0059 | E7: 2 | F7: 20240403 | G7: 20240430 | H7: PE000820001B | I7: WD14BVC2S6C.ABLGLGP | J7: 0 | K7: 2287.37 | L7: 2799 | M7: 10 | N7: 2134.83 | O7: 152.54 | P7: 4 | Q7: 0 | S7: 0 | V7: 610.16 | Z7: 0 | AA7: -10 | AB7: -1525.4 | AC7: ALL | AE7: 1-BASIC | AG7: 39 | AH7: 0 | AI7: 4 | AJ7: 0 | AK7: 4 | AL7: 0 | AM7: 0 | AN7: 0 | AO7: 0 | AP7: 0 | AQ7: 0 | AR7: 0 | AX7: APPROVED | AY7: 152.54 | AZ7: 14 | BA7: 2135.56 | BB7: 2135.56 | BC7: 0 | BD7: 0 | BE7: IMPORTACIONES RUBI S.A. | BF7: 2024 - RUBI - W/M - 20240403 AL 20240430 | BG7: WD14BVC2S6C.ABLGLGP | BH7: PEN | BI7: 1 | BJ7: 2799_10__ | BK7: PR-NTSO-20240327-0059WD14BVC2S6C.ABLGLGP
A8: 7 | B8: H&A Company | C8: W/M | D8: PR-NTSO-20240327-0059 | E8: 3 | F8: 20240403 | G8: 20240430 | H8: PE000820001B | I8: WD15EG2S.AESGLGP | J8: 0 | K8: 3393.31 | L8: 2949 | M8: 10 | N8: 2249.24 | O8: 1144.07 | P8: 2 | Q8: 0 | S8: 0 | V8: 2288.14 | Z8: 0 | AA8: -5 | AB8: -5720.35 | AC8: ALL | AE8: 1-BASIC | AG8: 14 | AH8: 0 | AI8: 2 | AJ8: 0 | AK8: 2 | AL8: 0 | AM8: 0 | AN8: 0 | AO8: 0 | AP8: 0 | AQ8: 0 | AR8: 0 | AX8: APPROVED | AY8: 1144.07 | AZ8: 7 | BA8: 8008.49 | BB8: 8008.49 | BC8: 0 | BD8: 0 | BE8: IMPORTACIONES RUBI S.A. | BF8: 2024 - RUBI - W/M - 20240403 AL 20240430 | BG8: WD15EG2S.AESGLGP | BH8: PEN | BI8: 1 | BJ8: 2949_10__ | BK8: PR-NTSO-20240327-0059WD15EG2S.AESGLGP
A9: 8 | B9: H&A Company | C9: W/M | D9: PR-NTSO-20240327-0059 | E9: 4 | F9: 20240403 | G9: 20240430 | H9: PE000820001B | I9: WT19BPB.ABMGLGP | J9: 0 | K9: 1372.12 | L9: 1399 | M9: 5 | N9: 1126.31 | O9: 245.81 | P9: 28 | Q9: 0 | S9: 0 | V9: 6882.68 | Z9: 0 | AA9: -2 | AB9: -491.62 | AC9: ALL | AE9: 1-BASIC | AG9: 29 | AH9: 0 | AI9: 28 | AJ9: 0 | AK9: 28 | AL9: 0 | AM9: 0 | AN9: 0 | AO9: 0 | AP9: 0 | AQ9: 0 | AR9: 0 | AX9: APPROVED | AY9: 245.81 | AZ9: 30 | BA9: 7374.3 | BB9: 7374.3 | BC9: 0 | BD9: 0 | BE9: IMPORTACIONES RUBI S.A. | BF9: 2024 - RUBI - W/M - 20240403 AL 20240430 | BG9: WT19BPB.ABMGLGP | BH9: PEN | BI9: 1 | BJ9: 1399_5__ | BK9: PR-NTSO-20240327-0059WT19BPB.ABMGLGP
A10: 9 | B10: H&A Company | C10: W/M | D10: PR-NTSO-20240416-0006 | E10: 1 | F10: 20240422 | G10: 20240430 | H10: PE000820001B | I10: WT13BPBK.ABMGLGP | J10: 0 | K10: 990.76 | L10: 1199 | M10: 10 | N10: 914.49 | O10: 76.27 | P10: 46 | Q10: 0 | S10: 0 | V10: 3508.42 | Z10: 0 | AA10: 6 | AB10: 457.62 | AC10: ALL | AE10: 1-BASIC | AG10: 101 | AH10: 0 | AI10: 46 | AJ10: 0 | AK10: 46 | AL10: 0 | AM10: 0 | AN10: 0 | AO10: 0 | AP10: 0 | AQ10: 0 | AR10: 0 | AX10: APPROVED | AY10: 76.27 | AZ10: 40 | BA10: 3050.8 | BB10: 3050.8 | BC10: 0 | BD10: 0 | BE10: IMPORTACIONES RUBI S.A. | BF10: 2024 - RUBI - W/M - 20240422 AL 20240430 | BG10: WT13BPBK.ABMGLGP | BH10: PEN | BI10: 1 | BJ10: 1199_10__ | BK10: PR-NTSO-20240416-0006WT13BPBK.ABMGLGP
A11: 10 | B11: H&A Company | C11: W/M | D11: PR-NTSO-20240416-0006 | E11: 2 | F11: 20240422 | G11: 20240430 | H11: PE000820001B | I11: WT17BV6.ABMGLGP | J11: 0 | K11: 1295.85 | L11: 1449 | M11: 8 | N11: 1129.73 | O11: 166.12 | P11: 5 | Q11: 0 | S11: 0 | V11: 830.6 | Z11: 0 | AA11: -35 | AB11: -5814.2 | AC11: ALL | AE11: 1-BASIC | AG11: 400 | AH11: 0 | AI11: 5 | AJ11: 0 | AK11: 5 | AL11: 0 | AM11: 0 | AN11: 0 | AO11: 0 | AP11: 0 | AQ11: 0 | AR11: 0 | AX11: APPROVED | AY11: 166.12 | AZ11: 40 | BA11: 6644.8 | BB11: 6644.8 | BC11: 0 | BD11: 0 | BE11: IMPORTACIONES RUBI S.A. | BF11: 2024 - RUBI - W/M - 20240422 AL 20240430 | BG11: WT17BV6.ABMGLGP | BH11: PEN | BI11: 1 | BJ11: 1449_8__ | BK11: PR-NTSO-20240416-0006WT17BV6.ABMGLGP

Sheet CALCULATE
A1: Seq | B1: Company Name | C1: Division Name | D1: Promotion No | E1: Promotion Line No | F1: Fecha Inicio | G1: Fecha Fin | H1: Customer Code | I1: Modelo | J1: PVP | K1: Costo Sellin | L1: * Precio Promotion | M1: * Nuevo Margen | N1: * Costo Promocion | O1: Diferencia | P1: Unidades | Q1: * Regalo | R1: * Bundle Cost | S1: * Bundle Cost Rate | T1: Bundle Diff | U1: Bundle Unidades | V1: Monto Total (Book) | W1: Monto Total | X1: Mix Adjust Amount | Y1: * NOTE * | Z1: FCST UNIT AMT DIFF | AA1: FCST QTY DIFF | AB1: FCST AMT DIFF | AC1: * ALL / SHOP / WEB | AD1: ADDITIONAL_COND | AE1: Priority | AF1: Ref Line | AG1: Stock | AH1: Sellin in Promo | AI1: Sellout Qty | AJ1: Return Qty | AK1: Promo Applied Qty | AL1: Customer Qty | AM1: * Limit Qty | AN1: Control Over Stock | AO1: Control Not Applied | AP1: Control Cust Request | AQ1: Control Below Cost | AR1: Control Limit | AS1: Bundle Seq | AT1: Bundle Priority | AU1: Bundle Stock | AV1: Bundle Sellout | AW1: Same Model | AX1: Promotion Line Status Code | AY1: FCST Unit Amt | AZ1: FCST Qty | BA1: FCST Amt | BB1: FCST Amt(Book) | BC1: Actual Accu Qty | BD1: Actual Accu Amt | BE1: Customer Name | BF1: Promotion Name | BG1: Model Code | BH1: Currency | BI1: TC | BJ1: Line Remark | BK1: Concate
A2: 1 | B2: H&A Company | C2: Cooking | D2: PR-NTSO-20240405-0031 | E2: 1 | F2: 20240410 | G2: 20240430 | H2: PE000820001B | I2: RSG314M.FSTGLPR | J2: 0 | K2: 1944.15 | L2: 1599 | M2: 10 | N2: 1219.58 | O2: 724.57 | P2: 8 | Q2: 0 | S2: 0 | V2: 5796.56 | Z2: 1.1368684e-13 | AA2: 0 | AB2: 9.094947e-13 | AC2: ALL | AE2: 1-BASIC | AG2: 18 | AH2: 0 | AI2: 18 | AJ2: 0 | AK2: 18 | AL2: 0 | AM2: 8 | AN2: 0 | AO2: 0 | AP2: 0 | AQ2: 0 | AR2: 10 | AX2: APPROVED | AY2: 724.57 | AZ2: 8 | BA2: 5796.56 | BB2: 5796.56 | BC2: 0 | BD2: 0 | BE2: IMPORTACIONES RUBI S.A. | BF2: 2024 - RUBI - Cooking - 20240410 AL 20240430 | BG2: RSG314M.FSTGLPR | BH2: PEN | BI2: 1 | BJ2: 1599_10__8 | BK2: PR-NTSO-20240405-0031RSG314M.FSTGLPR
A3: 2 | B3: H&A Company | C3: Cooking | D3: PR-NTSO-20240415-0011 | E3: 1 | F3: 20240420 | G3: 20240430 | H3: PE000820001B | I3: MS2596DIR.BBKGLPR | J3: 0 | K3: 365.34 | L3: 379 | M3: 10 | N3: 289.07 | O3: 76.27 | P3: 0 | Q3: 0 | S3: 0 | V3: 0 | Y3: COST UPDATED BY STOCK | Z3: -1.4210855e-14 | AA3: -21 | AB3: -1601.67 | AC3: ALL | AE3: 1-BASIC | AG3: 24 | AH3: 0 | AI3: 0 | AJ3: 0 | AK3: 0 | AL3: 0 | AM3: 0 | AN3: 0 | AO3: 0 | AP3: 0 | AQ3: 0 | AR3: 0 | AX3: APPROVED | AY3: 76.27 | AZ3: 21 | BA3: 1601.67 | BB3: 1601.67 | BC3: 0 | BD3: 0 | BE3: IMPORTACIONES RUBI S.A. | BF3: 2024 - RUBI - Cooking - 20240420 AL 20240430 | BG3: MS2596DIR.BBKGLPR | BH3: PEN | BI3: 1 | BJ3: 379_10__ | BK3: PR-NTSO-20240415-0011MS2596DIR.BBKGLPR
A4: 3 | B4: H&A Company | C4: Cooking | D4: PR-NTSO-20240416-0005 | E4: 1 | F4: 20240422 | G4: 20240430 | H4: PE000820001B | I4: MS4296DIR.BBKGLPR | J4: 0 | K4: 433.98 | L4: 539 | M4: 10 | N4: 411.1 | O4: 22.88 | P4: 0 | Q4: 0 | S4: 0 | V4: 0 | Y4: COST UPDATED BY STOCK | Z4: 15.25 | AA4: -140 | AB4: -1068.2 | AC4: ALL | AE4: 1-BASIC | AG4: 49 | AH4: 0 | AI4: 0 | AJ4: 0 | AK4: 0 | AL4: 0 | AM4: 0 | AN4: 0 | AO4: 0 | AP4: 0 | AQ4: 0 | AR4: 0 | AX4: APPROVED | AY4: 7.63 | AZ4: 140 | BA4: 1068.2 | BB4: 1068.2 | BC4: 0 | BD4: 0 | BE4: IMPORTACIONES RUBI S.A. | BF4: 2024 - RUBI - Cooking - 20240422 AL 20240430 | BG4: MS4296DIR.BBKGLPR | BH4: PEN | BI4: 1 | BJ4: 539_10__ | BK4: PR-NTSO-20240416-0005MS4296DIR.BBKGLPR
A5: 4 | B5: H&A Company | C5: Cooking | D5: PR-NTSO-20240416-0005 | E5: 2 | F5: 20240422 | G5: 20240430 | H5: PE000820001B | I5: RSG314M.FSTGLPR | J5: 0 | K5: 1219.58 | L5: 1599 | M5: 10 | N5: 1219.58 | O5: 0 | P5: 10 | Q5: 0 | S5: 0 | V5: 0 | Z5: -724.57 | AA5: 0 | AB5: -7245.7 | AC5: ALL | AE5: 2-ADDITIONAL | AF5: 1 | AG5: 10 | AH5: 0 | AI5: 10 | AJ5: 0 | AK5: 10 | AL5: 0 | AM5: 0 | AN5: 0 | AO5: 0 | AP5: 0 | AQ5: 0 | AR5: 0 | AX5: APPROVED | AY5: 724.57 | AZ5: 10 | BA5: 7245.7 | BB5: 7245.7 | BC5: 0 | BD5: 0 | BE5: IMPORTACIONES RUBI S.A. | BF5: 2024 - RUBI - Cooking - 20240422 AL 20240430 | BG5: RSG314M.FSTGLPR | BH5: PEN | BI5: 1 | BJ5: 1599_10__ | BK5: PR-NTSO-20240416-0005RSG314M.FSTGLPR
A6: 5 | B6: H&A Company | C6: W/M | D6: PR-NTSO-20240327-0059 | E6: 1 | F6: 20240403 | G6: 20240430 | H6: PE000820001B | I6: WD12BVC2S6C.ABLGLGP | J6: 0 | K6: 2279.75 | L6: 2099 | M6: 10 | N6: 1600.93 | O6: 678.82 | P6: 5 | Q6: 0 | S6: 0 | V6: 3394.1 | Z6: -1.1368684e-13 | AA6: -5 | AB6: -3394.1 | AC6: ALL | AE6: 1-BASIC | AG6: 36 | AH6: 0 | AI6: 5 | AJ6: 0 | AK6: 5 | AL6: 0 | AM6: 0 | AN6: 0 | AO6: 0 | AP6: 0 | AQ6: 0 | AR6: 0 | AX6: APPROVED | AY6: 678.82 | AZ6: 10 | BA6: 6788.2 | BB6: 6788.2 | BC6: 0 | BD6: 0 | BE6: IMPORTACIONES RUBI S.A. | BF6: 2024 - RUBI - W/M - 20240403 AL 20240430 | BG6: WD12BVC2S6C.ABLGLGP | BH6: PEN | BI6: 1 | BJ6: 2099_10__ | BK6: PR-NTSO-20240327-0059WD12BVC2S6C.ABLGLGP
A7: 6 | B7: H&A Company | C7: W/M | D7: PR-NTSO-20240327-0059 | E7: 2 | F7: 20240403 | G7: 20240430 | H7: PE000820001B | I7: WD14BVC2S6C.ABLGLGP | J7: 0 | K7: 2287.37 | L7: 2799 | M7: 10 | N7: 2134.83 | O7: 152.54 | P7: 4 | Q7: 0 | S7: 0 | V7: 610.16 | Z7: -2.8421709e-14 | AA7: -10 | AB7: -1525.4 | AC7: ALL | AE7: 1-BASIC | AG7: 39 | AH7: 0 | AI7: 4 | AJ7: 0 | AK7: 4 | AL7: 0 | AM7: 0 | AN7: 0 | AO7: 0 | AP7: 0 | AQ7: 0 | AR7: 0 | AX7: APPROVED | AY7: 152.54 | AZ7: 14 | BA7: 2135.56 | BB7: 2135.56 | BC7: 0 | BD7: 0 | BE7: IMPORTACIONES RUBI S.A. | BF7: 2024 - RUBI - W/M - 20240403 AL 20240430 | BG7: WD14BVC2S6C.ABLGLGP | BH7: PEN | BI7: 1 | BJ7: 2799_10__ | BK7: PR-NTSO-20240327-0059WD14BVC2S6C.ABLGLGP
A8: 7 | B8: H&A Company | C8: W/M | D8: PR-NTSO-20240327-0059 | E8: 3 | F8: 20240403 | G8: 20240430 | H8: PE000820001B | I8: WD15EG2S.AESGLGP | J8: 0 | K8: 3393.31 | L8: 2949 | M8: 10 | N8: 2249.24 | O8: 1144.07 | P8: 2 | Q8: 0 | S8: 0 | V8: 2288.14 | Z8: 2.2737368e-13 | AA8: -5 | AB8: -5720.35 | AC8: ALL | AE8: 1-BASIC | AG8: 14 | AH8: 0 | AI8: 2 | AJ8: 0 | AK8: 2 | AL8: 0 | AM8: 0 | AN8: 0 | AO8: 0 | AP8: 0 | AQ8: 0 | AR8: 0 | AX8: APPROVED | AY8: 1144.07 | AZ8: 7 | BA8: 8008.49 | BB8: 8008.49 | BC8: 0 | BD8: 0 | BE8: IMPORTACIONES RUBI S.A. | BF8: 2024 - RUBI - W/M - 20240403 AL 20240430 | BG8: WD15EG2S.AESGLGP | BH8: PEN | BI8: 1 | BJ8: 2949_10__ | BK8: PR-NTSO-20240327-0059WD15EG2S.AESGLGP
A9: 8 | B9: H&A Company | C9: W/M | D9: PR-NTSO-20240327-0059 | E9: 4 | F9: 20240403 | G9: 20240430 | H9: PE000820001B | I9: WT19BPB.ABMGLGP | J9: 0 | K9: 1372.12 | L9: 1399 | M9: 5 | N9: 1126.31 | O9: 245.81 | P9: 28 | Q9: 0 | S9: 0 | V9: 6882.68 | Z9: 1.7053026e-13 | AA9: -2 | AB9: -491.62 | AC9: ALL | AE9: 1-BASIC | AG9: 29 | AH9: 0 | AI9: 28 | AJ9: 0 | AK9: 28 | AL9: 0 | AM9: 0 | AN9: 0 | AO9: 0 | AP9: 0 | AQ9: 0 | AR9: 0 | AX9: APPROVED | AY9: 245.81 | AZ9: 30 | BA9: 7374.3 | BB9: 7374.3 | BC9: 0 | BD9: 0 | BE9: IMPORTACIONES RUBI S.A. | BF9: 2024 - RUBI - W/M - 20240403 AL 20240430 | BG9: WT19BPB.ABMGLGP | BH9: PEN | BI9: 1 | BJ9: 1399_5__ | BK9: PR-NTSO-20240327-0059WT19BPB.ABMGLGP
A10: 9 | B10: H&A Company | C10: W/M | D10: PR-NTSO-20240416-0006 | E10: 1 | F10: 20240422 | G10: 20240430 | H10: PE000820001B | I10: WT13BPBK.ABMGLGP | J10: 0 | K10: 990.76 | L10: 1199 | M10: 10 | N10: 914.49 | O10: 76.27 | P10: 46 | Q10: 0 | S10: 0 | V10: 3508.42 | Z10: -1.4210855e-14 | AA10: 6 | AB10: 457.62 | AC10: ALL | AE10: 1-BASIC | AG10: 101 | AH10: 0 | AI10: 46 | AJ10: 0 | AK10: 46 | AL10: 0 | AM10: 0 | AN10: 0 | AO10: 0 | AP10: 0 | AQ10: 0 | AR10: 0 | AX10: APPROVED | AY10: 76.27 | AZ10: 40 | BA10: 3050.8 | BB10: 3050.8 | BC10: 0 | BD10: 0 | BE10: IMPORTACIONES RUBI S.A. | BF10: 2024 - RUBI - W/M - 20240422 AL 20240430 | BG10: WT13BPBK.ABMGLGP | BH10: PEN | BI10: 1 | BJ10: 1199_10__ | BK10: PR-NTSO-20240416-0006WT13BPBK.ABMGLGP
A11: 10 | B11: H&A Company | C11: W/M | D11: PR-NTSO-20240416-0006 | E11: 2 | F11: 20240422 | G11: 20240430 | H11: PE000820001B | I11: WT17BV6.ABMGLGP | J11: 0 | K11: 1295.85 | L11: 1449 | M11: 8 | N11: 1129.73 | O11: 166.12 | P11: 5 | Q11: 0 | S11: 0 | V11: 830.6 | Z11: -1.1368684e-13 | AA11: -35 | AB11: -5814.2 | AC11: ALL | AE11: 1-BASIC | AG11: 400 | AH11: 0 | AI11: 5 | AJ11: 0 | AK11: 5 | AL11: 0 | AM11: 0 | AN11: 0 | AO11: 0 | AP11: 0 | AQ11: 0 | AR11: 0 | AX11: APPROVED | AY11: 166.12 | AZ11: 40 | BA11: 6644.8 | BB11: 6644.8 | BC11: 0 | BD11: 0 | BE11: IMPORTACIONES RUBI S.A. | BF11: 2024 - RUBI - W/M - 20240422 AL 20240430 | BG11: WT17BV6.ABMGLGP | BH11: PEN | BI11: 1 | BJ11: 1449_8__ | BK11: PR-NTSO-20240416-0006WT17BV6.ABMGLGP

Sheet SELLOUT
A1: CUSTOMER | B1: ACCT_GTM | C1: CUSTOMER_MODEL | D1: MODEL_CODE | E1: TXN_DATE | F1: CUST_STORE_CODE | G1: CUST_STORE_NAME | H1: SELLOUT_UNIT | I1: SELLOUT_AMT | J1: STOCK | K1: TICKET | L1: PROMO1_PRICE | M1: TARGET1_FLAG | N1: PROMO2_PRICE | O1: TARGET2_FLAG | P1: PROMO3_PRICE | Q1: TARGET3_FLAG | R1: PROMO4_PRICE | S1: TARGET4_FLAG | T1: PROMO5_PRICE | U1: TARGET5_FLAG | V1: PROMO6_PRICE | W1: TARGET6_FLAG | X1: PROMO7_PRICE | Y1: TARGET7_FLAG | Z1: PROMO8_PRICE | AA1: TARGET8_FLAG | AB1: PROMO9_PRICE | AC1: TARGET9_FLAG | AD1: PROMO10_PRICE | AE1: TARGET10_FLAG
A2: PE000820001B | B2: RUBI | C2: WD12BVC2S6C | D2: WD12BVC2S6C.ABLGLGP | E2: 45382 | J2: 36 | L2: 2099 | M2: STOCK
A3: PE000820001B | B3: RUBI | C3: WD14BVC2S6C.ABLGLGP | D3: WD14BVC2S6C.ABLGLGP | E3: 45382 | J3: 39 | L3: 2799 | M3: STOCK
A4: PE000820001B | B4: RUBI | C4: WD15EG2S | D4: WD15EG2S.AESGLGP | E4: 45382 | J4: 14 | L4: 2949 | M4: STOCK
A5: PE000820001B | B5: RUBI | C5: WT19BPB | D5: WT19BPB.ABMGLGP | E5: 45382 | J5: 29 | L5: 1399 | M5: STOCK
A6: PE000820001B | B6: RUBI | C6: WT19BPB | D6: WT19BPB.ABMGLGP | E6: 45385 | F6: 1 | G6: IMPORTACIONES RUBI LIMA | H6: 1 | I6: 1185.5932 | K6: 1399 | L6: 1399 | M6: PROMO APPLIED
A7: PE000820001B | B7: RUBI | C7: WT19BPB | D7: WT19BPB.ABMGLGP | E7: 45385 | F7: 1 | G7: IMPORTACIONES RUBI LIMA | H7: 1 | I7: 1185.5932 | K7: 1399 | L7: 1399 | M7: PROMO APPLIED
A8: PE000820001B | B8: RUBI | C8: WT19BPB | D8: WT19BPB.ABMGLGP | E8: 45385 | F8: 1 | G8: IMPORTACIONES RUBI LIMA | H8: 2 | I8: 2371.1864 | K8: 1399 | L8: 1399 | M8: PROMO APPLIED
A9: PE000820001B | B9: RUBI | C9: WD15EG2S | D9: WD15EG2S.AESGLGP | E9: 45387 | F9: 1 | G9: IMPORTACIONES RUBI LIMA | H9: 1 | I9: 2389.8305 | K9: 2820 | L9: 2949 | M9: PROMO APPLIED
A10: PE000820001B | B10: RUBI | C10: WT19BPB | D10: WT19BPB.ABMGLGP | E10: 45388 | F10: 1 | G10: IMPORTACIONES RUBI LIMA | H10: 13 | I10: 15412.712 | K10: 1399 | L10: 1399 | M10: PROMO APPLIED
A11: PE000820001B | B11: RUBI | C11: 8899552560 | D11: RSG314M.FSTGLPR | E11: 45389 | J11: 18 | L11: 1599 | M11: STOCK
A12: PE000820001B | B12: RUBI | C12: WD12BVC2S6C | D12: WD12BVC2S6C.ABLGLGP | E12: 45389 | J12: 36 | L12: 2099 | M12: STOCK
A13: PE000820001B | B13: RUBI | C13: WD14BVC2S6C.ABLGLGP | D13: WD14BVC2S6C.ABLGLGP | E13: 45389 | J13: 39 | L13: 2799 | M13: STOCK
A14: PE000820001B | B14: RUBI | C14: WD15EG2S | D14: WD15EG2S.AESGLGP | E14: 45389 | J14: 13 | L14: 2949 | M14: STOCK
A15: PE000820001B | B15: RUBI | C15: WT19BPB | D15: WT19BPB.ABMGLGP | E15: 45389 | J15: 12 | L15: 1399 | M15: STOCK
A16: PE000820001B | B16: RUBI | C16: WT19BPB | D16: WT19BPB.ABMGLGP | E16: 45390 | F16: 1 | G16: IMPORTACIONES RUBI LIMA | H16: 1 | I16: 1185.5932 | K16: 1399 | L16: 1399 | M16: PROMO APPLIED
A17: PE000820001B | B17: RUBI | C17: 8899552560 | D17: RSG314M.FSTGLPR | E17: 45394 | F17: 1 | G17: IMPORTACIONES RUBI LIMA | H17: 8 | I17: 10169.492 | K17: 1500 | L17: 1599 | M17: PROMO APPLIED
A18: PE000820001B | B18: RUBI | C18: WD14BVC2S6C.ABLGLGP | D18: WD14BVC2S6C.ABLGLGP | E18: 45394 | F18: 1 | G18: IMPORTACIONES RUBI LIMA | H18: 1 | I18: 2262.7119 | K18: 2670 | L18: 2799 | M18: PROMO APPLIED
A19: PE000820001B | B19: RUBI | C19: WT19BPB | D19: WT19BPB.ABMGLGP | E19: 45394 | F19: 1 | G19: IMPORTACIONES RUBI LIMA | H19: 1 | I19: 1185.5932 | K19: 1399 | L19: 1399 | M19: PROMO APPLIED
A20: PE000820001B | B20: RUBI | C20: WT19BPB | D20: WT19BPB.ABMGLGP | E20: 45394 | F20: 1 | G20: IMPORTACIONES RUBI LIMA | H20: 1 | I20: 1185.5932 | K20: 1399 | L20: 1399 | M20: PROMO APPLIED
A21: PE000820001B | B21: RUBI | C21: 8899552560 | D21: RSG314M.FSTGLPR | E21: 45396 | J21: 10 | L21: 1599 | M21: STOCK
A22: PE000820001B | B22: RUBI | C22: 8899552684 | D22: MS2596DIR.BBKGLPR | E22: 45396 | J22: 24 | L22: 379 | M22: STOCK
A23: PE000820001B | B23: RUBI | C23: WD12BVC2S6C | D23: WD12BVC2S6C.ABLGLGP | E23: 45396 | J23: 36 | L23: 2099 | M23: STOCK
A24: PE000820001B | B24: RUBI | C24: WD14BVC2S6C.ABLGLGP | D24: WD14BVC2S6C.ABLGLGP | E24: 45396 | J24: 38 | L24: 2799 | M24: STOCK
A25: PE000820001B | B25: RUBI | C25: WD15EG2S | D25: WD15EG2S.AESGLGP | E25: 45396 | J25: 13 | L25: 2949 | M25: STOCK
A26: PE000820001B | B26: RUBI | C26: WT19BPB | D26: WT19BPB.ABMGLGP | E26: 45396 | J26: 9 | L26: 1399 | M26: STOCK
A27: PE000820001B | B27: RUBI | C27: WD14BVC2S6C.ABLGLGP | D27: WD14BVC2S6C.ABLGLGP | E27: 45397 | F27: 2 | G27: IMPORTACIONES RUBI WEB | H27: 1 | I27: 2288.1356 | K27: 2700 | L27: 2799 | M27: PROMO APPLIED WEB
A28: PE000820001B | B28: RUBI | C28: WD14BVC2S6C.ABLGLGP | D28: WD14BVC2S6C.ABLGLGP | E28: 45397 | F28: 2 | G28: IMPORTACIONES RUBI WEB | H28: 1 | I28: 2288.1356 | K28: 2700 | L28: 2799 | M28: PROMO APPLIED WEB
A29: PE000820001B | B29: RUBI | C29: WT19BPB | D29: WT19BPB.ABMGLGP | E29: 45399 | F29: 1 | G29: IMPORTACIONES RUBI LIMA | H29: 1 | I29: 1185.5932 | K29: 1399 | L29: 1399 | M29: PROMO APPLIED
A30: PE000820001B | B30: RUBI | C30: WT19BPB | D30: WT19BPB.ABMGLGP | E30: 45399 | F30: 1 | G30: IMPORTACIONES RUBI LIMA | H30: 2 | I30: 2371.1864 | K30: 1399 | L30: 1399 | M30: PROMO APPLIED
A31: PE000820001B | B31: RUBI | C31: WD12BVC2S6C | D31: WD12BVC2S6C.ABLGLGP | E31: 45400 | F31: 1 | G31: IMPORTACIONES RUBI LIMA | H31: 1 | I31: 1694.9153 | K31: 2000.0001 | L31: 2099 | M31: PROMO APPLIED
A32: PE000820001B | B32: RUBI | C32: WD12BVC2S6C | D32: WD12BVC2S6C.ABLGLGP | E32: 45401 | F32: 1 | G32: IMPORTACIONES RUBI LIMA | H32: 1 | I32: 1694.9153 | K32: 2000.0001 | L32: 2099 | M32: PROMO APPLIED
A33: PE000820001B | B33: RUBI | C33: WD14BVC2S6C.ABLGLGP | D33: WD14BVC2S6C.ABLGLGP | E33: 45402 | F33: 2 | G33: IMPORTACIONES RUBI WEB | H33: 1 | I33: 2288.1356 | K33: 2700 | L33: 2799 | M33: PROMO APPLIED WEB
A34: PE000820001B | B34: RUBI | C34: 8899552560 | D34: RSG314M.FSTGLPR | E34: 45403 | J34: 10 | L34: 1599 | M34: STOCK
A35: PE000820001B | B35: RUBI | C35: 8899552602 | D35: MS4296DIR.BBKGLPR | E35: 45403 | J35: 49 | L35: 539 | M35: STOCK
A36: PE000820001B | B36: RUBI | C36: 8899552684 | D36: MS2596DIR.BBKGLPR | E36: 45403 | J36: 24 | L36: 379 | M36: STOCK
A37: PE000820001B | B37: RUBI | C37: WD12BVC2S6C | D37: WD12BVC2S6C.ABLGLGP | E37: 45403 | J37: 34 | L37: 2099 | M37: STOCK
A38: PE000820001B | B38: RUBI | C38: WD14BVC2S6C.ABLGLGP | D38: WD14BVC2S6C.ABLGLGP | E38: 45403 | J38: 35 | L38: 2799 | M38: STOCK
A39: PE000820001B | B39: RUBI | C39: WD15EG2S | D39: WD15EG2S.AESGLGP | E39: 45403 | J39: 13 | L39: 2949 | M39: STOCK
A40: PE000820001B | B40: RUBI | C40: WT13BPBK | D40: WT13BPBK.ABMGLGP | E40: 45403 | J40: 101 | L40: 1199 | M40: STOCK
A41: PE000820001B | B41: RUBI | C41: WT17BV6 | D41: WT17BV6.ABMGLGP | E41: 45403 | J41: 400 | L41: 1449 | M41: STOCK
A42: PE000820001B | B42: RUBI | C42: WT19BPB | D42: WT19BPB.ABMGLGP | E42: 45403 | J42: 6 | L42: 1399 | M42: STOCK
A43: PE000820001B | B43: RUBI | C43: WT19BPB | D43: WT19BPB.ABMGLGP | E43: 45404 | F43: 1 | G43: IMPORTACIONES RUBI LIMA | H43: 1 | I43: 1186.4407 | K43: 1400 | L43: 1399 | M43: PROMO APPLIED
A44: PE000820001B | B44: RUBI | C44: WT19BPB | D44: WT19BPB.ABMGLGP | E44: 45404 | F44: 1 | G44: IMPORTACIONES RUBI LIMA | H44: 1 | I44: 1186.4407 | K44: 1400 | L44: 1399 | M44: PROMO APPLIED
A45: PE000820001B | B45: RUBI | C45: WT19BPB | D45: WT19BPB.ABMGLGP | E45: 45404 | F45: 2 | G45: IMPORTACIONES RUBI WEB | H45: 2 | I45: 2372.8814 | K45: 1400 | L45: 1399 | M45: PROMO APPLIED WEB
A46: PE000820001B | B46: RUBI | C46: WD15EG2S | D46: WD15EG2S.AESGLGP | E46: 45405 | F46: 1 | G46: IMPORTACIONES RUBI LIMA | H46: 1 | I46: 2406.7797 | K46: 2840 | L46: 2949 | M46: PROMO APPLIED
A47: PE000820001B | B47: RUBI | C47: WT17BV6 | D47: WT17BV6.ABMGLGP | E47: 45405 | F47: 1 | G47: IMPORTACIONES RUBI LIMA | H47: 1 | I47: 1220.339 | K47: 1440 | L47: 1449 | M47: PROMO APPLIED
A48: PE000820001B | B48: RUBI | C48: WT19BPB | D48: WT19BPB.ABMGLGP | E48: 45405 | F48: 1 | G48: IMPORTACIONES RUBI LIMA | H48: 1 | I48: 1186.4407 | K48: 1400 | L48: 1399 | M48: PROMO APPLIED
A49: PE000820001B | B49: RUBI | C49: WT13BPBK | D49: WT13BPBK.ABMGLGP | E49: 45406 | F49: 1 | G49: IMPORTACIONES RUBI LIMA | H49: 46 | I49: 44441.458 | K49: 1140.02 | L49: 1199 | M49: PROMO APPLIED
A50: PE000820001B | B50: RUBI | C50: WT17BV6 | D50: WT17BV6.ABMGLGP | E50: 45406 | F50: 1 | G50: IMPORTACIONES RUBI LIMA | H50: 2 | I50: 2423.7288 | K50: 1430 | L50: 1449 | M50: PROMO APPLIED
A51: PE000820001B | B51: RUBI | C51: WD12BVC2S6C | D51: WD12BVC2S6C.ABLGLGP | E51: 45407 | F51: 1 | G51: IMPORTACIONES RUBI LIMA | H51: 1 | I51: 1686.4407 | K51: 1990 | L51: 2099 | M51: PROMO APPLIED
A52: PE000820001B | B52: RUBI | C52: 8899552560 | D52: RSG314M.FSTGLPR | E52: 45409 | F52: 1 | G52: IMPORTACIONES RUBI LIMA | H52: 10 | I52: 12881.356 | K52: 1520 | L52: 1599 | M52: PROMO APPLIED
A53: PE000820001B | B53: RUBI | C53: WD12BVC2S6C | D53: WD12BVC2S6C.ABLGLGP | E53: 45409 | F53: 1 | G53: IMPORTACIONES RUBI LIMA | H53: 2 | I53: 3389.8644 | K53: 2000.02 | L53: 2099 | M53: PROMO APPLIED
A54: PE000820001B | B54: RUBI | C54: WT17BV6 | D54: WT17BV6.ABMGLGP | E54: 45409 | F54: 1 | G54: IMPORTACIONES RUBI LIMA | H54: 1 | I54: 1211.8644 | K54: 1430 | L54: 1449 | M54: PROMO APPLIED
A55: PE000820001B | B55: RUBI | C55: WT17BV6 | D55: WT17BV6.ABMGLGP | E55: 45409 | F55: 1 | G55: IMPORTACIONES RUBI LIMA | H55: 1 | I55: 1220.339 | K55: 1440 | L55: 1449 | M55: PROMO APPLIED
A56: PE000820001B | B56: RUBI | C56: 8899552602 | D56: MS4296DIR.BBKGLPR | E56: 45410 | J56: 49 | L56: 539 | M56: STOCK
A57: PE000820001B | B57: RUBI | C57: 8899552684 | D57: MS2596DIR.BBKGLPR | E57: 45410 | J57: 24 | L57: 379 | M57: STOCK
A58: PE000820001B | B58: RUBI | C58: WD12BVC2S6C | D58: WD12BVC2S6C.ABLGLGP | E58: 45410 | J58: 31 | L58: 2099 | M58: STOCK
A59: PE000820001B | B59: RUBI | C59: WD14BVC2S6C.ABLGLGP | D59: WD14BVC2S6C.ABLGLGP | E59: 45410 | J59: 35 | L59: 2799 | M59: STOCK
A60: PE000820001B | B60: RUBI | C60: WD15EG2S | D60: WD15EG2S.AESGLGP | E60: 45410 | J60: 12 | L60: 2949 | M60: STOCK
A61: PE000820001B | B61: RUBI | C61: WT13BPBK | D61: WT13BPBK.ABMGLGP | E61: 45410 | J61: 55 | L61: 1199 | M61: STOCK
A62: PE000820001B | B62: RUBI | C62: WT17BV6 | D62: WT17BV6.ABMGLGP | E62: 45410 | J62: 395 | L62: 1449 | M62: STOCK
A63: PE000820001B | B63: RUBI | C63: WT19BPB | D63: WT19BPB.ABMGLGP | E63: 45410 | J63: 1 | L63: 1399 | M63: STOCK

Sheet SELLIN
A1: Seq | B1: Division Name | C1: Bill To Customer Code | D1: Item Name | E1: Sales YYYYMMDD | F1: Invoice NO | G1: ⁬Week-YYYYWWW | H1: Transaction Currency Code | I1: Sales Order Qty | J1: Unit Selling Price | K1: Sales Order Amount (Tax Exclude) | L1: TC | M1: Unit Selling Price (PEN) | N1: CAL SEQ1 | O1: NEW COST1 | P1: SELLOUT1 | Q1: STOCK1 | R1: CAL SEQ2 | S1: NEW COST2 | T1: SELLOUT2 | U1: STOCK2 | V1: CAL SEQ3 | W1: NEW COST3 | X1: SELLOUT3 | Y1: STOCK3 | Z1: CAL SEQ4 | AA1: NEW COST4 | AB1: SELLOUT4 | AC1: STOCK4 | AD1: CAL SEQ5 | AE1: NEW COST5 | AF1: SELLOUT5 | AG1: STOCK5 | AH1: CAL SEQ6 | AI1: NEW COST6 | AJ1: SELLOUT6 | AK1: STOCK6 | AL1: CAL SEQ7 | AM1: NEW COST7 | AN1: SELLOUT7 | AO1: STOCK7 | AP1: CAL SEQ8 | AQ1: NEW COST8 | AR1: SELLOUT8 | AS1: STOCK8 | AT1: CAL SEQ9 | AU1: NEW COST9 | AV1: SELLOUT9 | AW1: STOCK9 | AX1: CAL SEQ10 | AY1: NEW COST10 | AZ1: SELLOUT10 | BA1: STOCK10 | BB1: Bill To Customer Name | BC1: SO NO | BD1: SO Type Name
A2: 1 | B2: LTV | C2: PE000820001B | D2: MR23GN.AWP | E2: 20240424 | F2: 01-F001-00272671 | G2: 2024W13 | H2: PEN | I2: 200 | J2: 42 | K2: 8400 | L2: 3.701 | M2: 42 | N2: NA | O2: 0 | P2: 0 | Q2: 0 | R2: NA | S2: 0 | T2: 0 | U2: 0 | V2: NA | W2: 0 | X2: 0 | Y2: 0 | Z2: NA | AA2: 0 | AB2: 0 | AC2: 0 | AD2: NA | AE2: 0 | AF2: 0 | AG2: 0 | AH2: NA | AI2: 0 | AJ2: 0 | AK2: 0 | AL2: NA | AM2: 0 | AN2: 0 | AO2: 0 | AP2: NA | AQ2: 0 | AR2: 0 | AS2: 0 | AT2: NA | AU2: 0 | AV2: 0 | AW2: 0 | AX2: NA | AY2: 0 | AZ2: 0 | BA2: 0 | BB2: IMPORTACIONES RUBI S.A. | BC2: 1000442117 | BD2: REGULAR_OMD_PR
A3: 2 | B3: LTV | C3: PE000820001B | D3: MR23GN.AWP | E3: 20240228 | F3: 01-F001-00270000 | G3: 2024W08 | H3: PEN | I3: 79 | J3: 42 | K3: 3318 | L3: 3.793 | M3: 42 | N3: NA | O3: 0 | P3: 0 | Q3: 0 | R3: NA | S3: 0 | T3: 0 | U3: 0 | V3: NA | W3: 0 | X3: 0 | Y3: 0 | Z3: NA | AA3: 0 | AB3: 0 | AC3: 0 | AD3: NA | AE3: 0 | AF3: 0 | AG3: 0 | AH3: NA | AI3: 0 | AJ3: 0 | AK3: 0 | AL3: NA | AM3: 0 | AN3: 0 | AO3: 0 | AP3: NA | AQ3: 0 | AR3: 0 | AS3: 0 | AT3: NA | AU3: 0 | AV3: 0 | AW3: 0 | AX3: NA | AY3: 0 | AZ3: 0 | BA3: 0 | BB3: IMPORTACIONES RUBI S.A. | BC3: 1000439943 | BD3: REGULAR_OMD_PR
A4: 3 | B4: LTV | C4: PE000820001B | D4: MR23GN.AWP | E4: 20240228 | F4: 01-F001-00269999 | G4: 2024W04 | H4: PEN | I4: 100 | J4: 42 | K4: 4200 | L4: 3.793 | M4: 42 | N4: NA | O4: 0 | P4: 0 | Q4: 0 | R4: NA | S4: 0 | T4: 0 | U4: 0 | V4: NA | W4: 0 | X4: 0 | Y4: 0 | Z4: NA | AA4: 0 | AB4: 0 | AC4: 0 | AD4: NA | AE4: 0 | AF4: 0 | AG4: 0 | AH4: NA | AI4: 0 | AJ4: 0 | AK4: 0 | AL4: NA | AM4: 0 | AN4: 0 | AO4: 0 | AP4: NA | AQ4: 0 | AR4: 0 | AS4: 0 | AT4: NA | AU4: 0 | AV4: 0 | AW4: 0 | AX4: NA | AY4: 0 | AZ4: 0 | BA4: 0 | BB4: IMPORTACIONES RUBI S.A. | BC4: 1000438256 | BD4: REGULAR_OMD_PR
A5: 4 | B5: LTV | C5: PE000820001B | D5: MR23GN.AWP | E5: 20240227 | F5: 01-F001-00269910 | G5: 2024W04 | H5: PEN | I5: 200 | J5: 42 | K5: 8400 | L5: 3.803 | M5: 42 | N5: NA | O5: 0 | P5: 0 | Q5: 0 | R5: NA | S5: 0 | T5: 0 | U5: 0 | V5: NA | W5: 0 | X5: 0 | Y5: 0 | Z5: NA | AA5: 0 | AB5: 0 | AC5: 0 | AD5: NA | AE5: 0 | AF5: 0 | AG5: 0 | AH5: NA | AI5: 0 | AJ5: 0 | AK5: 0 | AL5: NA | AM5: 0 | AN5: 0 | AO5: 0 | AP5: NA | AQ5: 0 | AR5: 0 | AS5: 0 | AT5: NA | AU5: 0 | AV5: 0 | AW5: 0 | AX5: NA | AY5: 0 | AZ5: 0 | BA5: 0 | BB5: IMPORTACIONES RUBI S.A. | BC5: 1000438256 | BD5: REGULAR_OMD_PR
A6: 5 | B6: LTV | C6: PE000820001B | D6: MR23GN.AWP | E6: 20231027 | G6: 2023W43 | H6: PEN | I6: 100 | J6: 42 | K6: 4200 | L6: 3.872 | M6: 42 | N6: NA | O6: 0 | P6: 0 | Q6: 0 | R6: NA | S6: 0 | T6: 0 | U6: 0 | V6: NA | W6: 0 | X6: 0 | Y6: 0 | Z6: NA | AA6: 0 | AB6: 0 | AC6: 0 | AD6: NA | AE6: 0 | AF6: 0 | AG6: 0 | AH6: NA | AI6: 0 | AJ6: 0 | AK6: 0 | AL6: NA | AM6: 0 | AN6: 0 | AO6: 0 | AP6: NA | AQ6: 0 | AR6: 0 | AS6: 0 | AT6: NA | AU6: 0 | AV6: 0 | AW6: 0 | AX6: NA | AY6: 0 | AZ6: 0 | BA6: 0 | BB6: IMPORTACIONES RUBI S.A. | BC6: 1000433957 | BD6: REGULAR_OMD_PR
A7: 6 | B7: LTV | C7: PE000820001B | D7: MR23GN.AWP | E7: 20231027 | G7: 2023W43 | H7: PEN | I7: 200 | J7: 42 | K7: 8400 | L7: 3.872 | M7: 42 | N7: NA | O7: 0 | P7: 0 | Q7: 0 | R7: NA | S7: 0 | T7: 0 | U7: 0 | V7: NA | W7: 0 | X7: 0 | Y7: 0 | Z7: NA | AA7: 0 | AB7: 0 | AC7: 0 | AD7: NA | AE7: 0 | AF7: 0 | AG7: 0 | AH7: NA | AI7: 0 | AJ7: 0 | AK7: 0 | AL7: NA | AM7: 0 | AN7: 0 | AO7: 0 | AP7: NA | AQ7: 0 | AR7: 0 | AS7: 0 | AT7: NA | AU7: 0 | AV7: 0 | AW7: 0 | AX7: NA | AY7: 0 | AZ7: 0 | BA7: 0 | BB7: IMPORTACIONES RUBI S.A. | BC7: 1000433957 | BD7: REGULAR_OMD_PR
A8: 7 | B8: LTV | C8: PE000820001B | D8: MR23GN.AWP | E8: 20230930 | G8: 2023W39 | H8: PEN | I8: 50 | J8: 42 | K8: 2100 | L8: 3.797 | M8: 42 | N8: NA | O8: 0 | P8: 0 | Q8: 0 | R8: NA | S8: 0 | T8: 0 | U8: 0 | V8: NA | W8: 0 | X8: 0 | Y8: 0 | Z8: NA | AA8: 0 | AB8: 0 | AC8: 0 | AD8: NA | AE8: 0 | AF8: 0 | AG8: 0 | AH8: NA | AI8: 0 | AJ8: 0 | AK8: 0 | AL8: NA | AM8: 0 | AN8: 0 | AO8: 0 | AP8: NA | AQ8: 0 | AR8: 0 | AS8: 0 | AT8: NA | AU8: 0 | AV8: 0 | AW8: 0 | AX8: NA | AY8: 0 | AZ8: 0 | BA8: 0 | BB8: IMPORTACIONES RUBI S.A. | BC8: 1000432944 | BD8: REGULAR_OMD_PR
A9: 8 | B9: LTV | C9: PE000820001B | D9: MR23GN.AWP | E9: 20230929 | G9: 2023W39 | H9: PEN | I9: 100 | J9: 42 | K9: 4200 | L9: 3.806 | M9: 42 | N9: NA | O9: 0 | P9: 0 | Q9: 0 | R9: NA | S9: 0 | T9: 0 | U9: 0 | V9: NA | W9: 0 | X9: 0 | Y9: 0 | Z9: NA | AA9: 0 | AB9: 0 | AC9: 0 | AD9: NA | AE9: 0 | AF9: 0 | AG9: 0 | AH9: NA | AI9: 0 | AJ9: 0 | AK9: 0 | AL9: NA | AM9: 0 | AN9: 0 | AO9: 0 | AP9: NA | AQ9: 0 | AR9: 0 | AS9: 0 | AT9: NA | AU9: 0 | AV9: 0 | AW9: 0 | AX9: NA | AY9: 0 | AZ9: 0 | BA9: 0 | BB9: IMPORTACIONES RUBI S.A. | BC9: 1000432889 | BD9: REGULAR_OMD_PR
A10: 9 | B10: Cooking | C10: PE000820001B | D10: MS2596DIR.BBKGLPR | E10: 20230527 | F10: 01-F001-00257299 | G10: 2023W21 | H10: PEN | I10: 50 | J10: 365.34 | K10: 18267 | L10: 3.675 | M10: 365.34 | N10: 2 | O10: 365.34 | P10: 0 | Q10: 24 | R10: NA | S10: 0 | T10: 0 | U10: 0 | V10: NA | W10: 0 | X10: 0 | Y10: 0 | Z10: NA | AA10: 0 | AB10: 0 | AC10: 0 | AD10: NA | AE10: 0 | AF10: 0 | AG10: 0 | AH10: NA | AI10: 0 | AJ10: 0 | AK10: 0 | AL10: NA | AM10: 0 | AN10: 0 | AO10: 0 | AP10: NA | AQ10: 0 | AR10: 0 | AS10: 0 | AT10: NA | AU10: 0 | AV10: 0 | AW10: 0 | AX10: NA | AY10: 0 | AZ10: 0 | BA10: 0 | BB10: IMPORTACIONES RUBI S.A. | BC10: 1000427925 | BD10: REGULAR_OMD_PR
A11: 10 | B11: Cooking | C11: PE000820001B | D11: MS2596DIR.BBKGLPR | E11: 20230223 | G11: 2023W02 | H11: PEN | I11: 15 | J11: 365.34 | K11: 5480.1 | L11: 3.827 | M11: 365.34 | N11: NA | O11: 0 | P11: 0 | Q11: 0 | R11: NA | S11: 0 | T11: 0 | U11: 0 | V11: NA | W11: 0 | X11: 0 | Y11: 0 | Z11: NA | AA11: 0 | AB11: 0 | AC11: 0 | AD11: NA | AE11: 0 | AF11: 0 | AG11: 0 | AH11: NA | AI11: 0 | AJ11: 0 | AK11: 0 | AL11: NA | AM11: 0 | AN11: 0 | AO11: 0 | AP11: NA | AQ11: 0 | AR11: 0 | AS11: 0 | AT11: NA | AU11: 0 | AV11: 0 | AW11: 0 | AX11: NA | AY11: 0 | AZ11: 0 | BA11: 0 | BB11: IMPORTACIONES RUBI S.A. | BC11: 1000422908 | BD11: REGULAR_OMD_PR
A12: 11 | B12: Cooking | C12: PE000820001B | D12: MS2596DIR.BBKGLPR | E12: 20230203 | G12: 2022W50 | H12: PEN | I12: 15 | J12: 365.34 | K12: 5480.1 | L12: 3.835 | M12: 365.34 | N12: NA | O12: 0 | P12: 0 | Q12: 0 | R12: NA | S12: 0 | T12: 0 | U12: 0 | V12: NA | W12: 0 | X12: 0 | Y12: 0 | Z12: NA | AA12: 0 | AB12: 0 | AC12: 0 | AD12: NA | AE12: 0 | AF12: 0 | AG12: 0 | AH12: NA | AI12: 0 | AJ12: 0 | AK12: 0 | AL12: NA | AM12: 0 | AN12: 0 | AO12: 0 | AP12: NA | AQ12: 0 | AR12: 0 | AS12: 0 | AT12: NA | AU12: 0 | AV12: 0 | AW12: 0 | AX12: NA | AY12: 0 | AZ12: 0 | BA12: 0 | BB12: IMPORTACIONES RUBI S.A. | BC12: 1000422292 | BD12: REGULAR_OMD_PR
A13: 12 | B13: Cooking | C13: PE000820001B | D13: MS2596DIR.BBKGLPR | E13: 20230131 | F13: 01-F001-00251305 | G13: 2022W50 | H13: PEN | I13: 3 | J13: 365.34 | K13: 1096.02 | L13: 3.859 | M13: 365.34 | N13: NA | O13: 0 | P13: 0 | Q13: 0 | R13: NA | S13: 0 | T13: 0 | U13: 0 | V13: NA | W13: 0 | X13: 0 | Y13: 0 | Z13: NA | AA13: 0 | AB13: 0 | AC13: 0 | AD13: NA | AE13: 0 | AF13: 0 | AG13: 0 | AH13: NA | AI13: 0 | AJ13: 0 | AK13: 0 | AL13: NA | AM13: 0 | AN13: 0 | AO13: 0 | AP13: NA | AQ13: 0 | AR13: 0 | AS13: 0 | AT13: NA | AU13: 0 | AV13: 0 | AW13: 0 | AX13: NA | AY13: 0 | AZ13: 0 | BA13: 0 | BB13: IMPORTACIONES RUBI S.A. | BC13: 1000422292 | BD13: REGULAR_OMD_PR
A14: 13 | B14: Cooking | C14: PE000820001B | D14: MS2596DIR.BBKGLPR | E14: 20230126 | G14: 2022W50 | H14: PEN | I14: 2 | J14: 365.34 | K14: 730.68 | L14: 3.9 | M14: 365.34 | N14: NA | O14: 0 | P14: 0 | Q14: 0 | R14: NA | S14: 0 | T14: 0 | U14: 0 | V14: NA | W14: 0 | X14: 0 | Y14: 0 | Z14: NA | AA14: 0 | AB14: 0 | AC14: 0 | AD14: NA | AE14: 0 | AF14: 0 | AG14: 0 | AH14: NA | AI14: 0 | AJ14: 0 | AK14: 0 | AL14: NA | AM14: 0 | AN14: 0 | AO14: 0 | AP14: NA | AQ14: 0 | AR14: 0 | AS14: 0 | AT14: NA | AU14: 0 | AV14: 0 | AW14: 0 | AX14: NA | AY14: 0 | AZ14: 0 | BA14: 0 | BB14: IMPORTACIONES RUBI S.A. | BC14: 1000422292 | BD14: REGULAR_OMD_PR
A15: 14 | B15: Cooking | C15: PE000820001B | D15: MS2596DIR.BBKGLPR | E15: 20221222 | F15: 01-F001-00249968 | G15: 2022W50 | H15: PEN | I15: 20 | J15: 365.34 | K15: 7306.8 | L15: 3.825 | M15: 365.34 | N15: NA | O15: 0 | P15: 0 | Q15: 0 | R15: NA | S15: 0 | T15: 0 | U15: 0 | V15: NA | W15: 0 | X15: 0 | Y15: 0 | Z15: NA | AA15: 0 | AB15: 0 | AC15: 0 | AD15: NA | AE15: 0 | AF15: 0 | AG15: 0 | AH15: NA | AI15: 0 | AJ15: 0 | AK15: 0 | AL15: NA | AM15: 0 | AN15: 0 | AO15: 0 | AP15: NA | AQ15: 0 | AR15: 0 | AS15: 0 | AT15: NA | AU15: 0 | AV15: 0 | AW15: 0 | AX15: NA | AY15: 0 | AZ15: 0 | BA15: 0 | BB15: IMPORTACIONES RUBI S.A. | BC15: 1000422292 | BD15: REGULAR_OMD_PR
A16: 15 | B16: Cooking | C16: PE000820001B | D16: MS2596DIR.BBKGLPR | E16: 20220408 | G16: 2022W12 | H16: PEN | I16: 50 | J16: 357.71 | K16: 17885.5 | L16: 3.714 | M16: 357.71 | N16: NA | O16: 0 | P16: 0 | Q16: 0 | R16: NA | S16: 0 | T16: 0 | U16: 0 | V16: NA | W16: 0 | X16: 0 | Y16: 0 | Z16: NA | AA16: 0 | AB16: 0 | AC16: 0 | AD16: NA | AE16: 0 | AF16: 0 | AG16: 0 | AH16: NA | AI16: 0 | AJ16: 0 | AK16: 0 | AL16: NA | AM16: 0 | AN16: 0 | AO16: 0 | AP16: NA | AQ16: 0 | AR16: 0 | AS16: 0 | AT16: NA | AU16: 0 | AV16: 0 | AW16: 0 | AX16: NA | AY16: 0 | AZ16: 0 | BA16: 0 | BB16: IMPORTACIONES RUBI S.A. | BC16: 1000414682 | BD16: REGULAR_OMD_PR
A17: 16 | B17: Cooking | C17: PE000820001B | D17: MS2596DIR.BBKGLPR | E17: 20220408 | G17: 2022W14 | H17: PEN | I17: -1 | J17: 357.71 | K17: -357.71 | L17: 3.714 | M17: 357.71 | N17: NA | O17: 0 | P17: 0 | Q17: 0 | R17: NA | S17: 0 | T17: 0 | U17: 0 | V17: NA | W17: 0 | X17: 0 | Y17: 0 | Z17: NA | AA17: 0 | AB17: 0 | AC17: 0 | AD17: NA | AE17: 0 | AF17: 0 | AG17: 0 | AH17: NA | AI17: 0 | AJ17: 0 | AK17: 0 | AL17: NA | AM17: 0 | AN17: 0 | AO17: 0 | AP17: NA | AQ17: 0 | AR17: 0 | AS17: 0 | AT17: NA | AU17: 0 | AV17: 0 | AW17: 0 | AX17: NA | AY17: 0 | AZ17: 0 | BA17: 0 | BB17: IMPORTACIONES RUBI S.A. | BC17: 3000025867 | BD17: GOODSET_RETURN_OMD_PR
A18: 17 | B18: Cooking | C18: PE000820001B | D18: MS2596DIR.BBKGLPR | E18: 20220120 | G18: 2022W02 | H18: PEN | I18: 5 | J18: 388.22 | K18: 1941.1 | L18: 3.866 | M18: 388.22 | N18: NA | O18: 0 | P18: 0 | Q18: 0 | R18: NA | S18: 0 | T18: 0 | U18: 0 | V18: NA | W18: 0 | X18: 0 | Y18: 0 | Z18: NA | AA18: 0 | AB18: 0 | AC18: 0 | AD18: NA | AE18: 0 | AF18: 0 | AG18: 0 | AH18: NA | AI18: 0 | AJ18: 0 | AK18: 0 | AL18: NA | AM18: 0 | AN18: 0 | AO18: 0 | AP18: NA | AQ18: 0 | AR18: 0 | AS18: 0 | AT18: NA | AU18: 0 | AV18: 0 | AW18: 0 | AX18: NA | AY18: 0 | AZ18: 0 | BA18: 0 | BB18: IMPORTACIONES RUBI S.A. | BC18: 1000412314 | BD18: REGULAR_OMD_PR
A19: 18 | B19: Cooking | C19: PE000820001B | D19: MS2596DIR.BBKGLPR | E19: 20211127 | G19: 2021W45 | H19: PEN | I19: 2 | J19: 372.97 | K19: 745.94 | L19: 4.041 | M19: 372.97 | N19: NA | O19: 0 | P19: 0 | Q19: 0 | R19: NA | S19: 0 | T19: 0 | U19: 0 | V19: NA | W19: 0 | X19: 0 | Y19: 0 | Z19: NA | AA19: 0 | AB19: 0 | AC19: 0 | AD19: NA | AE19: 0 | AF19: 0 | AG19: 0 | AH19: NA | AI19: 0 | AJ19: 0 | AK19: 0 | AL19: NA | AM19: 0 | AN19: 0 | AO19: 0 | AP19: NA | AQ19: 0 | AR19: 0 | AS19: 0 | AT19: NA | AU19: 0 | AV19: 0 | AW19: 0 | AX19: NA | AY19: 0 | AZ19: 0 | BA19: 0 | BB19: IMPORTACIONES RUBI S.A. | BC19: 1000410428 | BD19: REGULAR_OMD_PR
A20: 19 | B20: Cooking | C20: PE000820001B | D20: MS2596DIR.BBKGLPR | E20: 20211126 | G20: 2021W47 | H20: PEN | I20: 7 | J20: 372.97 | K20: 2610.79 | L20: 4.031 | M20: 372.97 | N20: NA | O20: 0 | P20: 0 | Q20: 0 | R20: NA | S20: 0 | T20: 0 | U20: 0 | V20: NA | W20: 0 | X20: 0 | Y20: 0 | Z20: NA | AA20: 0 | AB20: 0 | AC20: 0 | AD20: NA | AE20: 0 | AF20: 0 | AG20: 0 | AH20: NA | AI20: 0 | AJ20: 0 | AK20: 0 | AL20: NA | AM20: 0 | AN20: 0 | AO20: 0 | AP20: NA | AQ20: 0 | AR20: 0 | AS20: 0 | AT20: NA | AU20: 0 | AV20: 0 | AW20: 0 | AX20: NA | AY20: 0 | AZ20: 0 | BA20: 0 | BB20: IMPORTACIONES RUBI S.A. | BC20: 1000410826 | BD20: REGULAR_OMD_PR
A21: 20 | B21: Cooking | C21: PE000820001B | D21: MS2596DIR.BBKGLPR | E21: 20211126 | F21: 01-F001-00230214 | G21: 2021W43 | H21: PEN | I21: 8 | J21: 372.97 | K21: 2983.76 | L21: 4.031 | M21: 372.97 | N21: NA | O21: 0 | P21: 0 | Q21: 0 | R21: NA | S21: 0 | T21: 0 | U21: 0 | V21: NA | W21: 0 | X21: 0 | Y21: 0 | Z21: NA | AA21: 0 | AB21: 0 | AC21: 0 | AD21: NA | AE21: 0 | AF21: 0 | AG21: 0 | AH21: NA | AI21: 0 | AJ21: 0 | AK21: 0 | AL21: NA | AM21: 0 | AN21: 0 | AO21: 0 | AP21: NA | AQ21: 0 | AR21: 0 | AS21: 0 | AT21: NA | AU21: 0 | AV21: 0 | AW21: 0 | AX21: NA | AY21: 0 | AZ21: 0 | BA21: 0 | BB21: IMPORTACIONES RUBI S.A. | BC21: 1000410134 | BD21: REGULAR_OMD_PR
A22: 21 | B22: Cooking | C22: PE000820001B | D22: MS2596DIR.BBKGLPR | E22: 20211126 | F22: 01-F001-00230196 | G22: 2021W44 | H22: PEN | I22: 8 | J22: 372.97 | K22: 2983.76 | L22: 4.031 | M22: 372.97 | N22: NA | O22: 0 | P22: 0 | Q22: 0 | R22: NA | S22: 0 | T22: 0 | U22: 0 | V22: NA | W22: 0 | X22: 0 | Y22: 0 | Z22: NA | AA22: 0 | AB22: 0 | AC22: 0 | AD22: NA | AE22: 0 | AF22: 0 | AG22: 0 | AH22: NA | AI22: 0 | AJ22: 0 | AK22: 0 | AL22: NA | AM22: 0 | AN22: 0 | AO22: 0 | AP22: NA | AQ22: 0 | AR22: 0 | AS22: 0 | AT22: NA | AU22: 0 | AV22: 0 | AW22: 0 | AX22: NA | AY22: 0 | AZ22: 0 | BA22: 0 | BB22: IMPORTACIONES RUBI S.A. | BC22: 1000410406 | BD22: REGULAR_OMD_PR
A23: 22 | B23: Cooking | C23: PE000820001B | D23: MS2596DIR.BBKGLPR | E23: 20210925 | F23: 01-F001-00226125 | G23: 2021W38 | H23: PEN | I23: 10 | J23: 372.97 | K23: 3729.7 | L23: 4.111 | M23: 372.97 | N23: NA | O23: 0 | P23: 0 | Q23: 0 | R23: NA | S23: 0 | T23: 0 | U23: 0 | V23: NA | W23: 0 | X23: 0 | Y23: 0 | Z23: NA | AA23: 0 | AB23: 0 | AC23: 0 | AD23: NA | AE23: 0 | AF23: 0 | AG23: 0 | AH23: NA | AI23: 0 | AJ23: 0 | AK23: 0 | AL23: NA | AM23: 0 | AN23: 0 | AO23: 0 | AP23: NA | AQ23: 0 | AR23: 0 | AS23: 0 | AT23: NA | AU23: 0 | AV23: 0 | AW23: 0 | AX23: NA | AY23: 0 | AZ23: 0 | BA23: 0 | BB23: IMPORTACIONES RUBI S.A. | BC23: 1000409085 | BD23: REGULAR_OMD_PR
A24: 23 | B24: Cooking | C24: PE000820001B | D24: MS2596DIR.BBKGLPR | E24: 20210311 | G24: 2021W10 | H24: PEN | I24: 5 | J24: 327.2 | K24: 1636 | L24: 3.696 | M24: 327.2 | N24: NA | O24: 0 | P24: 0 | Q24: 0 | R24: NA | S24: 0 | T24: 0 | U24: 0 | V24: NA | W24: 0 | X24: 0 | Y24: 0 | Z24: NA | AA24: 0 | AB24: 0 | AC24: 0 | AD24: NA | AE24: 0 | AF24: 0 | AG24: 0 | AH24: NA | AI24: 0 | AJ24: 0 | AK24: 0 | AL24: NA | AM24: 0 | AN24: 0 | AO24: 0 | AP24: NA | AQ24: 0 | AR24: 0 | AS24: 0 | AT24: NA | AU24: 0 | AV24: 0 | AW24: 0 | AX24: NA | AY24: 0 | AZ24: 0 | BA24: 0 | BB24: IMPORTACIONES RUBI S.A. | BC24: 1000403660 | BD24: REGULAR_OMD_PR
A25: 24 | B25: Cooking | C25: PE000820001B | D25: MS2596DIR.BBKGLPR | E25: 20210219 | G25: 2021W02 | H25: PEN | I25: 3 | J25: 334.83 | K25: 1004.49 | L25: 3.652 | M25: 334.83 | N25: NA | O25: 0 | P25: 0 | Q25: 0 | R25: NA | S25: 0 | T25: 0 | U25: 0 | V25: NA | W25: 0 | X25: 0 | Y25: 0 | Z25: NA | AA25: 0 | AB25: 0 | AC25: 0 | AD25: NA | AE25: 0 | AF25: 0 | AG25: 0 | AH25: NA | AI25: 0 | AJ25: 0 | AK25: 0 | AL25: NA | AM25: 0 | AN25: 0 | AO25: 0 | AP25: NA | AQ25: 0 | AR25: 0 | AS25: 0 | AT25: NA | AU25: 0 | AV25: 0 | AW25: 0 | AX25: NA | AY25: 0 | AZ25: 0 | BA25: 0 | BB25: IMPORTACIONES RUBI S.A. | BC25: 1000401569 | BD25: REGULAR_OMD_PR
A26: 25 | B26: Cooking | C26: PE000820001B | D26: MS2596DIR.BBKGLPR | E26: 20210219 | G26: 2021W02 | H26: PEN | I26: 10 | J26: 334.83 | K26: 3348.3 | L26: 3.652 | M26: 334.83 | N26: NA | O26: 0 | P26: 0 | Q26: 0 | R26: NA | S26: 0 | T26: 0 | U26: 0 | V26: NA | W26: 0 | X26: 0 | Y26: 0 | Z26: NA | AA26: 0 | AB26: 0 | AC26: 0 | AD26: NA | AE26: 0 | AF26: 0 | AG26: 0 | AH26: NA | AI26: 0 | AJ26: 0 | AK26: 0 | AL26: NA | AM26: 0 | AN26: 0 | AO26: 0 | AP26: NA | AQ26: 0 | AR26: 0 | AS26: 0 | AT26: NA | AU26: 0 | AV26: 0 | AW26: 0 | AX26: NA | AY26: 0 | AZ26: 0 | BA26: 0 | BB26: IMPORTACIONES RUBI S.A. | BC26: 1000401573 | BD26: REGULAR_OMD_PR
A27: 26 | B27: Cooking | C27: PE000820001B | D27: MS2596DIR.BBKGLPR | E27: 20210218 | G27: 2021W02 | H27: PEN | I27: 2 | J27: 334.83 | K27: 669.66 | L27: 3.655 | M27: 334.83 | N27: NA | O27: 0 | P27: 0 | Q27: 0 | R27: NA | S27: 0 | T27: 0 | U27: 0 | V27: NA | W27: 0 | X27: 0 | Y27: 0 | Z27: NA | AA27: 0 | AB27: 0 | AC27: 0 | AD27: NA | AE27: 0 | AF27: 0 | AG27: 0 | AH27: NA | AI27: 0 | AJ27: 0 | AK27: 0 | AL27: NA | AM27: 0 | AN27: 0 | AO27: 0 | AP27: NA | AQ27: 0 | AR27: 0 | AS27: 0 | AT27: NA | AU27: 0 | AV27: 0 | AW27: 0 | AX27: NA | AY27: 0 | AZ27: 0 | BA27: 0 | BB27: IMPORTACIONES RUBI S.A. | BC27: 1000401647 | BD27: REGULAR_OMD_PR
A28: 27 | B28: Cooking | C28: PE000820001B | D28: MS2596DIR.BBKGLPR | E28: 20210116 | F28: 01-F001-00205073 | G28: 2020W46 | H28: PEN | I28: 1 | J28: 327.2 | K28: 327.2 | L28: 3.614 | M28: 327.2 | N28: NA | O28: 0 | P28: 0 | Q28: 0 | R28: NA | S28: 0 | T28: 0 | U28: 0 | V28: NA | W28: 0 | X28: 0 | Y28: 0 | Z28: NA | AA28: 0 | AB28: 0 | AC28: 0 | AD28: NA | AE28: 0 | AF28: 0 | AG28: 0 | AH28: NA | AI28: 0 | AJ28: 0 | AK28: 0 | AL28: NA | AM28: 0 | AN28: 0 | AO28: 0 | AP28: NA | AQ28: 0 | AR28: 0 | AS28: 0 | AT28: NA | AU28: 0 | AV28: 0 | AW28: 0 | AX28: NA | AY28: 0 | AZ28: 0 | BA28: 0 | BB28: IMPORTACIONES RUBI S.A. | BC28: 1000399718 | BD28: REGULAR_OMD_PR
A29: 28 | B29: Cooking | C29: PE000820001B | D29: MS2596DIR.BBKGLPR | E29: 20210116 | F29: 01-F001-00205058 | G29: 2020W46 | H29: PEN | I29: 1 | J29: 327.2 | K29: 327.2 | L29: 3.614 | M29: 327.2 | N29: NA | O29: 0 | P29: 0 | Q29: 0 | R29: NA | S29: 0 | T29: 0 | U29: 0 | V29: NA | W29: 0 | X29: 0 | Y29: 0 | Z29: NA | AA29: 0 | AB29: 0 | AC29: 0 | AD29: NA | AE29: 0 | AF29: 0 | AG29: 0 | AH29: NA | AI29: 0 | AJ29: 0 | AK29: 0 | AL29: NA | AM29: 0 | AN29: 0 | AO29: 0 | AP29: NA | AQ29: 0 | AR29: 0 | AS29: 0 | AT29: NA | AU29: 0 | AV29: 0 | AW29: 0 | AX29: NA | AY29: 0 | AZ29: 0 | BA29: 0 | BB29: IMPORTACIONES RUBI S.A. | BC29: 1000399636 | BD29: REGULAR_OMD_PR
A30: 29 | B30: Cooking | C30: PE000820001B | D30: MS4296DIR.BBKGLPR | E30: 20240227 | G30: 2024W08 | H30: PEN | I30: 5 | J30: 418.73 | K30: 2093.65 | L30: 3.803 | M30: 418.73 | N30: 3 | O30: 433.98 | Q30: 5 | R30: NA | S30: 0 | T30: 0 | U30: 0 | V30: NA | W30: 0 | X30: 0 | Y30: 0 | Z30: NA | AA30: 0 | AB30: 0 | AC30: 0 | AD30: NA | AE30: 0 | AF30: 0 | AG30: 0 | AH30: NA | AI30: 0 | AJ30: 0 | AK30: 0 | AL30: NA | AM30: 0 | AN30: 0 | AO30: 0 | AP30: NA | AQ30: 0 | AR30: 0 | AS30: 0 | AT30: NA | AU30: 0 | AV30: 0 | AW30: 0 | AX30: NA | AY30: 0 | AZ30: 0 | BA30: 0 | BB30: IMPORTACIONES RUBI S.A. | BC30: 1000439898 | BD30: REGULAR_OMD_PR
A31: 30 | B31: Cooking | C31: PE000820001B | D31: MS4296DIR.BBKGLPR | E31: 20230727 | F31: 01-F001-00259861 | G31: 2023W21 | H31: PEN | I31: 48 | J31: 433.98 | K31: 20831.04 | L31: 3.602 | M31: 433.98 | N31: 3 | O31: 433.98 | P31: 0 | Q31: 44 | R31: NA | S31: 0 | T31: 0 | U31: 0 | V31: NA | W31: 0 | X31: 0 | Y31: 0 | Z31: NA | AA31: 0 | AB31: 0 | AC31: 0 | AD31: NA | AE31: 0 | AF31: 0 | AG31: 0 | AH31: NA | AI31: 0 | AJ31: 0 | AK31: 0 | AL31: NA | AM31: 0 | AN31: 0 | AO31: 0 | AP31: NA | AQ31: 0 | AR31: 0 | AS31: 0 | AT31: NA | AU31: 0 | AV31: 0 | AW31: 0 | AX31: NA | AY31: 0 | AZ31: 0 | BA31: 0 | BB31: IMPORTACIONES RUBI S.A. | BC31: 1000427925 | BD31: REGULAR_OMD_PR
A32: 31 | B32: Cooking | C32: PE000820001B | D32: MS4296DIR.BBKGLPR | E32: 20230527 | G32: 2023W21 | H32: PEN | I32: 4 | J32: 433.98 | K32: 1735.92 | L32: 3.675 | M32: 433.98 | N32: NA | O32: 0 | P32: 0 | Q32: 0 | R32: NA | S32: 0 | T32: 0 | U32: 0 | V32: NA | W32: 0 | X32: 0 | Y32: 0 | Z32: NA | AA32: 0 | AB32: 0 | AC32: 0 | AD32: NA | AE32: 0 | AF32: 0 | AG32: 0 | AH32: NA | AI32: 0 | AJ32: 0 | AK32: 0 | AL32: NA | AM32: 0 | AN32: 0 | AO32: 0 | AP32: NA | AQ32: 0 | AR32: 0 | AS32: 0 | AT32: NA | AU32: 0 | AV32: 0 | AW32: 0 | AX32: NA | AY32: 0 | AZ32: 0 | BA32: 0 | BB32: IMPORTACIONES RUBI S.A. | BC32: 1000427925 | BD32: REGULAR_OMD_PR
A33: 32 | B33: Cooking | C33: PE000820001B | D33: MS4296DIR.BBKGLPR | E33: 20230228 | F33: 01-F001-00252838 | G33: 2023W08 | H33: PEN | I33: 27 | J33: 433.98 | K33: 11717.46 | L33: 3.816 | M33: 433.98 | N33: NA | O33: 0 | P33: 0 | Q33: 0 | R33: NA | S33: 0 | T33: 0 | U33: 0 | V33: NA | W33: 0 | X33: 0 | Y33: 0 | Z33: NA | AA33: 0 | AB33: 0 | AC33: 0 | AD33: NA | AE33: 0 | AF33: 0 | AG33: 0 | AH33: NA | AI33: 0 | AJ33: 0 | AK33: 0 | AL33: NA | AM33: 0 | AN33: 0 | AO33: 0 | AP33: NA | AQ33: 0 | AR33: 0 | AS33: 0 | AT33: NA | AU33: 0 | AV33: 0 | AW33: 0 | AX33: NA | AY33: 0 | AZ33: 0 | BA33: 0 | BB33: IMPORTACIONES RUBI S.A. | BC33: 1000424246 | BD33: REGULAR_OMD_PR
A34: 33 | B34: Cooking | C34: PE000820001B | D34: MS4296DIR.BBKGLPR | E34: 20230130 | F34: 01-F001-00251245 | G34: 2023W02 | H34: PEN | I34: 20 | J34: 433.98 | K34: 8679.6 | L34: 3.829 | M34: 433.98 | N34: NA | O34: 0 | P34: 0 | Q34: 0 | R34: NA | S34: 0 | T34: 0 | U34: 0 | V34: NA | W34: 0 | X34: 0 | Y34: 0 | Z34: NA | AA34: 0 | AB34: 0 | AC34: 0 | AD34: NA | AE34: 0 | AF34: 0 | AG34: 0 | AH34: NA | AI34: 0 | AJ34: 0 | AK34: 0 | AL34: NA | AM34: 0 | AN34: 0 | AO34: 0 | AP34: NA | AQ34: 0 | AR34: 0 | AS34: 0 | AT34: NA | AU34: 0 | AV34: 0 | AW34: 0 | AX34: NA | AY34: 0 | AZ34: 0 | BA34: 0 | BB34: IMPORTACIONES RUBI S.A. | BC34: 1000422908 | BD34: REGULAR_OMD_PR
A35: 34 | B35: Cooking | C35: PE000820001B | D35: MS4296DIR.BBKGLPR | E35: 20220930 | G35: 2022W39 | H35: PEN | I35: 10 | J35: 433.98 | K35: 4339.8 | L35: 3.971 | M35: 433.98 | N35: NA | O35: 0 | P35: 0 | Q35: 0 | R35: NA | S35: 0 | T35: 0 | U35: 0 | V35: NA | W35: 0 | X35: 0 | Y35: 0 | Z35: NA | AA35: 0 | AB35: 0 | AC35: 0 | AD35: NA | AE35: 0 | AF35: 0 | AG35: 0 | AH35: NA | AI35: 0 | AJ35: 0 | AK35: 0 | AL35: NA | AM35: 0 | AN35: 0 | AO35: 0 | AP35: NA | AQ35: 0 | AR35: 0 | AS35: 0 | AT35: NA | AU35: 0 | AV35: 0 | AW35: 0 | AX35: NA | AY35: 0 | AZ35: 0 | BA35: 0 | BB35: IMPORTACIONES RUBI S.A. | BC35: 1000419825 | BD35: REGULAR_OMD_PR
A36: 35 | B36: Cooking | C36: PE000820001B | D36: MS4296DIR.BBKGLPR | E36: 20220408 | G36: 2022W12 | H36: PEN | I36: 50 | J36: 426.36 | K36: 21318 | L36: 3.714 | M36: 426.36 | N36: NA | O36: 0 | P36: 0 | Q36: 0 | R36: NA | S36: 0 | T36: 0 | U36: 0 | V36: NA | W36: 0 | X36: 0 | Y36: 0 | Z36: NA | AA36: 0 | AB36: 0 | AC36: 0 | AD36: NA | AE36: 0 | AF36: 0 | AG36: 0 | AH36: NA | AI36: 0 | AJ36: 0 | AK36: 0 | AL36: NA | AM36: 0 | AN36: 0 | AO36: 0 | AP36: NA | AQ36: 0 | AR36: 0 | AS36: 0 | AT36: NA | AU36: 0 | AV36: 0 | AW36: 0 | AX36: NA | AY36: 0 | AZ36: 0 | BA36: 0 | BB36: IMPORTACIONES RUBI S.A. | BC36: 1000414682 | BD36: REGULAR_OMD_PR
A37: 36 | B37: Cooking | C37: PE000820001B | D37: MS4296DIR.BBKGLPR | E37: 20211217 | G37: 2021W50 | H37: PEN | I37: 14 | J37: 449.24 | K37: 6289.36 | L37: 4.04 | M37: 449.24 | N37: NA | O37: 0 | P37: 0 | Q37: 0 | R37: NA | S37: 0 | T37: 0 | U37: 0 | V37: NA | W37: 0 | X37: 0 | Y37: 0 | Z37: NA | AA37: 0 | AB37: 0 | AC37: 0 | AD37: NA | AE37: 0 | AF37: 0 | AG37: 0 | AH37: NA | AI37: 0 | AJ37: 0 | AK37: 0 | AL37: NA | AM37: 0 | AN37: 0 | AO37: 0 | AP37: NA | AQ37: 0 | AR37: 0 | AS37: 0 | AT37: NA | AU37: 0 | AV37: 0 | AW37: 0 | AX37: NA | AY37: 0 | AZ37: 0 | BA37: 0 | BB37: IMPORTACIONES RUBI S.A. | BC37: 1000411402 | BD37: REGULAR_OMD_PR
A38: 37 | B38: Cooking | C38: PE000820001B | D38: MS4296DIR.BBKGLPR | E38: 20211127 | F38: 01-F001-00230500 | G38: 2021W43 | H38: PEN | I38: 6 | J38: 456.86 | K38: 2741.16 | L38: 4.041 | M38: 456.86 | N38: NA | O38: 0 | P38: 0 | Q38: 0 | R38: NA | S38: 0 | T38: 0 | U38: 0 | V38: NA | W38: 0 | X38: 0 | Y38: 0 | Z38: NA | AA38: 0 | AB38: 0 | AC38: 0 | AD38: NA | AE38: 0 | AF38: 0 | AG38: 0 | AH38: NA | AI38: 0 | AJ38: 0 | AK38: 0 | AL38: NA | AM38: 0 | AN38: 0 | AO38: 0 | AP38: NA | AQ38: 0 | AR38: 0 | AS38: 0 | AT38: NA | AU38: 0 | AV38: 0 | AW38: 0 | AX38: NA | AY38: 0 | AZ38: 0 | BA38: 0 | BB38: IMPORTACIONES RUBI S.A. | BC38: 1000410134 | BD38: REGULAR_OMD_PR
A39: 38 | B39: Cooking | C39: PE000820001B | D39: MS4296DIR.BBKGLPR | E39: 20211126 | F39: 01-F001-00230210 | G39: 2021W44 | H39: PEN | I39: 8 | J39: 456.86 | K39: 3654.88 | L39: 4.031 | M39: 456.86 | N39: NA | O39: 0 | P39: 0 | Q39: 0 | R39: NA | S39: 0 | T39: 0 | U39: 0 | V39: NA | W39: 0 | X39: 0 | Y39: 0 | Z39: NA | AA39: 0 | AB39: 0 | AC39: 0 | AD39: NA | AE39: 0 | AF39: 0 | AG39: 0 | AH39: NA | AI39: 0 | AJ39: 0 | AK39: 0 | AL39: NA | AM39: 0 | AN39: 0 | AO39: 0 | AP39: NA | AQ39: 0 | AR39: 0 | AS39: 0 | AT39: NA | AU39: 0 | AV39: 0 | AW39: 0 | AX39: NA | AY39: 0 | AZ39: 0 | BA39: 0 | BB39: IMPORTACIONES RUBI S.A. | BC39: 1000410406 | BD39: REGULAR_OMD_PR
A40: 39 | B40: Cooking | C40: PE000820001B | D40: MS4296DIR.BBKGLPR | E40: 20211113 | F40: 01-F001-00229116 | G40: 2021W43 | H40: PEN | I40: 2 | J40: 456.86 | K40: 913.72 | L40: 4.026 | M40: 456.86 | N40: NA | O40: 0 | P40: 0 | Q40: 0 | R40: NA | S40: 0 | T40: 0 | U40: 0 | V40: NA | W40: 0 | X40: 0 | Y40: 0 | Z40: NA | AA40: 0 | AB40: 0 | AC40: 0 | AD40: NA | AE40: 0 | AF40: 0 | AG40: 0 | AH40: NA | AI40: 0 | AJ40: 0 | AK40: 0 | AL40: NA | AM40: 0 | AN40: 0 | AO40: 0 | AP40: NA | AQ40: 0 | AR40: 0 | AS40: 0 | AT40: NA | AU40: 0 | AV40: 0 | AW40: 0 | AX40: NA | AY40: 0 | AZ40: 0 | BA40: 0 | BB40: IMPORTACIONES RUBI S.A. | BC40: 1000410134 | BD40: REGULAR_OMD_PR
A41: 40 | B41: Cooking | C41: PE000820001B | D41: MS4296DIR.BBKGLPR | E41: 20211022 | F41: 01-F001-00227810 | G41: 2021W36 | H41: PEN | I41: 6 | J41: 449.24 | K41: 2695.44 | L41: 3.953 | M41: 449.24 | N41: NA | O41: 0 | P41: 0 | Q41: 0 | R41: NA | S41: 0 | T41: 0 | U41: 0 | V41: NA | W41: 0 | X41: 0 | Y41: 0 | Z41: NA | AA41: 0 | AB41: 0 | AC41: 0 | AD41: NA | AE41: 0 | AF41: 0 | AG41: 0 | AH41: NA | AI41: 0 | AJ41: 0 | AK41: 0 | AL41: NA | AM41: 0 | AN41: 0 | AO41: 0 | AP41: NA | AQ41: 0 | AR41: 0 | AS41: 0 | AT41: NA | AU41: 0 | AV41: 0 | AW41: 0 | AX41: NA | AY41: 0 | AZ41: 0 | BA41: 0 | BB41: IMPORTACIONES RUBI S.A. | BC41: 1000408637 | BD41: REGULAR_OMD_PR
A42: 41 | B42: Cooking | C42: PE000820001B | D42: MS4296DIR.BBKGLPR | E42: 20210925 | F42: 01-F001-00226131 | G42: 2021W36 | H42: PEN | I42: 4 | J42: 449.24 | K42: 1796.96 | L42: 4.111 | M42: 449.24 | N42: NA | O42: 0 | P42: 0 | Q42: 0 | R42: NA | S42: 0 | T42: 0 | U42: 0 | V42: NA | W42: 0 | X42: 0 | Y42: 0 | Z42: NA | AA42: 0 | AB42: 0 | AC42: 0 | AD42: NA | AE42: 0 | AF42: 0 | AG42: 0 | AH42: NA | AI42: 0 | AJ42: 0 | AK42: 0 | AL42: NA | AM42: 0 | AN42: 0 | AO42: 0 | AP42: NA | AQ42: 0 | AR42: 0 | AS42: 0 | AT42: NA | AU42: 0 | AV42: 0 | AW42: 0 | AX42: NA | AY42: 0 | AZ42: 0 | BA42: 0 | BB42: IMPORTACIONES RUBI S.A. | BC42: 1000408637 | BD42: REGULAR_OMD_PR
A43: 42 | B43: Cooking | C43: PE000820001B | D43: MS4296DIR.BBKGLPR | E43: 20210816 | G43: 2021W31 | H43: PEN | I43: 2 | J43: 426.36 | K43: 852.72 | L43: 4.081 | M43: 426.36 | N43: NA | O43: 0 | P43: 0 | Q43: 0 | R43: NA | S43: 0 | T43: 0 | U43: 0 | V43: NA | W43: 0 | X43: 0 | Y43: 0 | Z43: NA | AA43: 0 | AB43: 0 | AC43: 0 | AD43: NA | AE43: 0 | AF43: 0 | AG43: 0 | AH43: NA | AI43: 0 | AJ43: 0 | AK43: 0 | AL43: NA | AM43: 0 | AN43: 0 | AO43: 0 | AP43: NA | AQ43: 0 | AR43: 0 | AS43: 0 | AT43: NA | AU43: 0 | AV43: 0 | AW43: 0 | AX43: NA | AY43: 0 | AZ43: 0 | BA43: 0 | BB43: IMPORTACIONES RUBI S.A. | BC43: 1000407840 | BD43: REGULAR_OMD_PR
A44: 43 | B44: Cooking | C44: PE000820001B | D44: MS4296DIR.BBKGLPR | E44: 20210331 | G44: 2021W10 | H44: PEN | I44: 1 | J44: 411.1 | K44: 411.1 | L44: 3.763 | M44: 411.1 | N44: NA | O44: 0 | P44: 0 | Q44: 0 | R44: NA | S44: 0 | T44: 0 | U44: 0 | V44: NA | W44: 0 | X44: 0 | Y44: 0 | Z44: NA | AA44: 0 | AB44: 0 | AC44: 0 | AD44: NA | AE44: 0 | AF44: 0 | AG44: 0 | AH44: NA | AI44: 0 | AJ44: 0 | AK44: 0 | AL44: NA | AM44: 0 | AN44: 0 | AO44: 0 | AP44: NA | AQ44: 0 | AR44: 0 | AS44: 0 | AT44: NA | AU44: 0 | AV44: 0 | AW44: 0 | AX44: NA | AY44: 0 | AZ44: 0 | BA44: 0 | BB44: IMPORTACIONES RUBI S.A. | BC44: 1000403660 | BD44: REGULAR_OMD_PR
A45: 44 | B45: Cooking | C45: PE000820001B | D45: MS4296DIR.BBKGLPR | E45: 20210326 | G45: 2021W10 | H45: PEN | I45: 2 | J45: 411.1 | K45: 822.2 | L45: 3.734 | M45: 411.1 | N45: NA | O45: 0 | P45: 0 | Q45: 0 | R45: NA | S45: 0 | T45: 0 | U45: 0 | V45: NA | W45: 0 | X45: 0 | Y45: 0 | Z45: NA | AA45: 0 | AB45: 0 | AC45: 0 | AD45: NA | AE45: 0 | AF45: 0 | AG45: 0 | AH45: NA | AI45: 0 | AJ45: 0 | AK45: 0 | AL45: NA | AM45: 0 | AN45: 0 | AO45: 0 | AP45: NA | AQ45: 0 | AR45: 0 | AS45: 0 | AT45: NA | AU45: 0 | AV45: 0 | AW45: 0 | AX45: NA | AY45: 0 | AZ45: 0 | BA45: 0 | BB45: IMPORTACIONES RUBI S.A. | BC45: 1000403660 | BD45: REGULAR_OMD_PR
A46: 45 | B46: Cooking | C46: PE000820001B | D46: MS4296DIR.BBKGLPR | E46: 20210311 | G46: 2021W10 | H46: PEN | I46: 1 | J46: 411.1 | K46: 411.1 | L46: 3.696 | M46: 411.1 | N46: NA | O46: 0 | P46: 0 | Q46: 0 | R46: NA | S46: 0 | T46: 0 | U46: 0 | V46: NA | W46: 0 | X46: 0 | Y46: 0 | Z46: NA | AA46: 0 | AB46: 0 | AC46: 0 | AD46: NA | AE46: 0 | AF46: 0 | AG46: 0 | AH46: NA | AI46: 0 | AJ46: 0 | AK46: 0 | AL46: NA | AM46: 0 | AN46: 0 | AO46: 0 | AP46: NA | AQ46: 0 | AR46: 0 | AS46: 0 | AT46: NA | AU46: 0 | AV46: 0 | AW46: 0 | AX46: NA | AY46: 0 | AZ46: 0 | BA46: 0 | BB46: IMPORTACIONES RUBI S.A. | BC46: 1000403660 | BD46: REGULAR_OMD_PR
A47: 46 | B47: Cooking | C47: PE000820001B | D47: MS4296DIR.BBKGLPR | E47: 20210219 | G47: 2021W05 | H47: PEN | I47: 9 | J47: 418.73 | K47: 3768.57 | L47: 3.652 | M47: 418.73 | N47: NA | O47: 0 | P47: 0 | Q47: 0 | R47: NA | S47: 0 | T47: 0 | U47: 0 | V47: NA | W47: 0 | X47: 0 | Y47: 0 | Z47: NA | AA47: 0 | AB47: 0 | AC47: 0 | AD47: NA | AE47: 0 | AF47: 0 | AG47: 0 | AH47: NA | AI47: 0 | AJ47: 0 | AK47: 0 | AL47: NA | AM47: 0 | AN47: 0 | AO47: 0 | AP47: NA | AQ47: 0 | AR47: 0 | AS47: 0 | AT47: NA | AU47: 0 | AV47: 0 | AW47: 0 | AX47: NA | AY47: 0 | AZ47: 0 | BA47: 0 | BB47: IMPORTACIONES RUBI S.A. | BC47: 1000402635 | BD47: REGULAR_OMD_PR
A48: 47 | B48: Cooking | C48: PE000820001B | D48: MS4296DIR.BBKGLPR | E48: 20210218 | F48: 01-F001-00207876 | G48: 2021W05 | H48: PEN | I48: 1 | J48: 418.73 | K48: 418.73 | L48: 3.655 | M48: 418.73 | N48: NA | O48: 0 | P48: 0 | Q48: 0 | R48: NA | S48: 0 | T48: 0 | U48: 0 | V48: NA | W48: 0 | X48: 0 | Y48: 0 | Z48: NA | AA48: 0 | AB48: 0 | AC48: 0 | AD48: NA | AE48: 0 | AF48: 0 | AG48: 0 | AH48: NA | AI48: 0 | AJ48: 0 | AK48: 0 | AL48: NA | AM48: 0 | AN48: 0 | AO48: 0 | AP48: NA | AQ48: 0 | AR48: 0 | AS48: 0 | AT48: NA | AU48: 0 | AV48: 0 | AW48: 0 | AX48: NA | AY48: 0 | AZ48: 0 | BA48: 0 | BB48: IMPORTACIONES RUBI S.A. | BC48: 1000402644 | BD48: REGULAR_OMD_PR
A49: 48 | B49: Cooking | C49: PE000820001B | D49: MS4296DIR.BBKGLPR | E49: 20210115 | G49: 2020W50 | H49: PEN | I49: 2 | J49: 418.73 | K49: 837.46 | L49: 3.613 | M49: 418.73 | N49: NA | O49: 0 | P49: 0 | Q49: 0 | R49: NA | S49: 0 | T49: 0 | U49: 0 | V49: NA | W49: 0 | X49: 0 | Y49: 0 | Z49: NA | AA49: 0 | AB49: 0 | AC49: 0 | AD49: NA | AE49: 0 | AF49: 0 | AG49: 0 | AH49: NA | AI49: 0 | AJ49: 0 | AK49: 0 | AL49: NA | AM49: 0 | AN49: 0 | AO49: 0 | AP49: NA | AQ49: 0 | AR49: 0 | AS49: 0 | AT49: NA | AU49: 0 | AV49: 0 | AW49: 0 | AX49: NA | AY49: 0 | AZ49: 0 | BA49: 0 | BB49: IMPORTACIONES RUBI S.A. | BC49: 1000400701 | BD49: REGULAR_OMD_PR
A50: 49 | B50: Cooking | C50: PE000820001B | D50: RSG314M.FSTGLPR | E50: 20221130 | G50: 2022W48 | H50: PEN | I50: 44 | J50: 1944.15 | K50: 85542.6 | L50: 3.847 | M50: 1944.15 | N50: 1 | O50: 1944.15 | P50: 8 | Q50: 18 | R50: NA | S50: 0 | T50: 0 | U50: 0 | V50: NA | W50: 0 | X50: 0 | Y50: 0 | Z50: NA | AA50: 0 | AB50: 0 | AC50: 0 | AD50: NA | AE50: 0 | AF50: 0 | AG50: 0 | AH50: NA | AI50: 0 | AJ50: 0 | AK50: 0 | AL50: NA | AM50: 0 | AN50: 0 | AO50: 0 | AP50: NA | AQ50: 0 | AR50: 0 | AS50: 0 | AT50: NA | AU50: 0 | AV50: 0 | AW50: 0 | AX50: NA | AY50: 0 | AZ50: 0 | BA50: 0 | BB50: IMPORTACIONES RUBI S.A. | BC50: 1000421866 | BD50: REGULAR_OMD_PR
A51: 50 | B51: Cooking | C51: PE000820001B | D51: RSG314M.FSTGLPR | E51: 20221130 | G51: 2022W48 | H51: PEN | I51: -5 | J51: 1944.15 | K51: -9720.75 | L51: 3.847 | M51: 1944.15 | N51: NA | O51: 0 | P51: 0 | Q51: 0 | R51: NA | S51: 0 | T51: 0 | U51: 0 | V51: NA | W51: 0 | X51: 0 | Y51: 0 | Z51: NA | AA51: 0 | AB51: 0 | AC51: 0 | AD51: NA | AE51: 0 | AF51: 0 | AG51: 0 | AH51: NA | AI51: 0 | AJ51: 0 | AK51: 0 | AL51: NA | AM51: 0 | AN51: 0 | AO51: 0 | AP51: NA | AQ51: 0 | AR51: 0 | AS51: 0 | AT51: NA | AU51: 0 | AV51: 0 | AW51: 0 | AX51: NA | AY51: 0 | AZ51: 0 | BA51: 0 | BB51: IMPORTACIONES RUBI S.A. | BC51: 3000027355 | BD51: GOODSET_RETURN_OMD_PR
A52: 51 | B52: Cooking | C52: PE000820001B | D52: RSG314M.FSTGLPR | E52: 20210730 | F52: 01-F001-00222468 | G52: 2021W29 | H52: PEN | I52: 15 | J52: 1753.47 | K52: 26302.05 | L52: 3.924 | M52: 1753.47 | N52: NA | O52: 0 | P52: 0 | Q52: 0 | R52: NA | S52: 0 | T52: 0 | U52: 0 | V52: NA | W52: 0 | X52: 0 | Y52: 0 | Z52: NA | AA52: 0 | AB52: 0 | AC52: 0 | AD52: NA | AE52: 0 | AF52: 0 | AG52: 0 | AH52: NA | AI52: 0 | AJ52: 0 | AK52: 0 | AL52: NA | AM52: 0 | AN52: 0 | AO52: 0 | AP52: NA | AQ52: 0 | AR52: 0 | AS52: 0 | AT52: NA | AU52: 0 | AV52: 0 | AW52: 0 | AX52: NA | AY52: 0 | AZ52: 0 | BA52: 0 | BB52: IMPORTACIONES RUBI S.A. | BC52: 1000407571 | BD52: REGULAR_OMD_PR
A53: 52 | B53: Cooking | C53: PE000820001B | D53: RSG314M.FSTGLPR | E53: 20210410 | G53: 2021W10 | H53: PEN | I53: 1 | J53: 1751.8 | K53: 1751.8 | L53: 3.624 | M53: 1751.8 | N53: NA | O53: 0 | P53: 0 | Q53: 0 | R53: NA | S53: 0 | T53: 0 | U53: 0 | V53: NA | W53: 0 | X53: 0 | Y53: 0 | Z53: NA | AA53: 0 | AB53: 0 | AC53: 0 | AD53: NA | AE53: 0 | AF53: 0 | AG53: 0 | AH53: NA | AI53: 0 | AJ53: 0 | AK53: 0 | AL53: NA | AM53: 0 | AN53: 0 | AO53: 0 | AP53: NA | AQ53: 0 | AR53: 0 | AS53: 0 | AT53: NA | AU53: 0 | AV53: 0 | AW53: 0 | AX53: NA | AY53: 0 | AZ53: 0 | BA53: 0 | BB53: IMPORTACIONES RUBI S.A. | BC53: 1000403688 | BD53: REGULAR_OMD_PR
A54: 53 | B54: Cooking | C54: PE000820001B | D54: RSG314M.FSTGLPR | E54: 20210128 | G54: 2021W02 | H54: PEN | I54: 3 | J54: 1789.08 | K54: 5367.24 | L54: 3.653 | M54: 1789.08 | N54: NA | O54: 0 | P54: 0 | Q54: 0 | R54: NA | S54: 0 | T54: 0 | U54: 0 | V54: NA | W54: 0 | X54: 0 | Y54: 0 | Z54: NA | AA54: 0 | AB54: 0 | AC54: 0 | AD54: NA | AE54: 0 | AF54: 0 | AG54: 0 | AH54: NA | AI54: 0 | AJ54: 0 | AK54: 0 | AL54: NA | AM54: 0 | AN54: 0 | AO54: 0 | AP54: NA | AQ54: 0 | AR54: 0 | AS54: 0 | AT54: NA | AU54: 0 | AV54: 0 | AW54: 0 | AX54: NA | AY54: 0 | AZ54: 0 | BA54: 0 | BB54: IMPORTACIONES RUBI S.A. | BC54: 1000401569 | BD54: REGULAR_OMD_PR
A55: 54 | B55: Cooking | C55: PE000820001B | D55: RSG314M.FSTGLPR | E55: 20210128 | F55: 01-F001-00206395 | G55: 2021W01 | H55: PEN | I55: 2 | J55: 1789.08 | K55: 3578.16 | L55: 3.653 | M55: 1789.08 | N55: NA | O55: 0 | P55: 0 | Q55: 0 | R55: NA | S55: 0 | T55: 0 | U55: 0 | V55: NA | W55: 0 | X55: 0 | Y55: 0 | Z55: NA | AA55: 0 | AB55: 0 | AC55: 0 | AD55: NA | AE55: 0 | AF55: 0 | AG55: 0 | AH55: NA | AI55: 0 | AJ55: 0 | AK55: 0 | AL55: NA | AM55: 0 | AN55: 0 | AO55: 0 | AP55: NA | AQ55: 0 | AR55: 0 | AS55: 0 | AT55: NA | AU55: 0 | AV55: 0 | AW55: 0 | AX55: NA | AY55: 0 | AZ55: 0 | BA55: 0 | BB55: IMPORTACIONES RUBI S.A. | BC55: 1000401492 | BD55: REGULAR_OMD_PR
A56: 55 | B56: Cooking | C56: PE000820001B | D56: RSG314M.FSTGLPR | E56: 20210111 | G56: 2021W01 | H56: PEN | I56: 1 | J56: 1789.08 | K56: 1789.08 | L56: 3.615 | M56: 1789.08 | N56: NA | O56: 0 | P56: 0 | Q56: 0 | R56: NA | S56: 0 | T56: 0 | U56: 0 | V56: NA | W56: 0 | X56: 0 | Y56: 0 | Z56: NA | AA56: 0 | AB56: 0 | AC56: 0 | AD56: NA | AE56: 0 | AF56: 0 | AG56: 0 | AH56: NA | AI56: 0 | AJ56: 0 | AK56: 0 | AL56: NA | AM56: 0 | AN56: 0 | AO56: 0 | AP56: NA | AQ56: 0 | AR56: 0 | AS56: 0 | AT56: NA | AU56: 0 | AV56: 0 | AW56: 0 | AX56: NA | AY56: 0 | AZ56: 0 | BA56: 0 | BB56: IMPORTACIONES RUBI S.A. | BC56: 1000401490 | BD56: REGULAR_OMD_PR
A57: 56 | B57: W/M | C57: PE000820001B | D57: WD12BVC2S6C.ABLGLGP | E57: 20221031 | G57: 2022W43 | H57: PEN | I57: 80 | J57: 2279.75 | K57: 182380 | L57: 3.978 | M57: 2279.75 | N57: 5 | O57: 2279.75 | P57: 5 | Q57: 36 | R57: NA | S57: 0 | T57: 0 | U57: 0 | V57: NA | W57: 0 | X57: 0 | Y57: 0 | Z57: NA | AA57: 0 | AB57: 0 | AC57: 0 | AD57: NA | AE57: 0 | AF57: 0 | AG57: 0 | AH57: NA | AI57: 0 | AJ57: 0 | AK57: 0 | AL57: NA | AM57: 0 | AN57: 0 | AO57: 0 | AP57: NA | AQ57: 0 | AR57: 0 | AS57: 0 | AT57: NA | AU57: 0 | AV57: 0 | AW57: 0 | AX57: NA | AY57: 0 | AZ57: 0 | BA57: 0 | BB57: IMPORTACIONES RUBI S.A. | BC57: 1000420826 | BD57: REGULAR_OMD_PR
A58: 57 | B58: W/M | C58: PE000820001B | D58: WD12BVC2S6C.ABLGLGP | E58: 20220630 | F58: 01-F001-00242605 | G58: 2022W26 | H58: PEN | I58: 12 | J58: 1600.93 | K58: 19211.16 | L58: 3.788 | M58: 1600.93 | N58: NA | O58: 0 | P58: 0 | Q58: 0 | R58: NA | S58: 0 | T58: 0 | U58: 0 | V58: NA | W58: 0 | X58: 0 | Y58: 0 | Z58: NA | AA58: 0 | AB58: 0 | AC58: 0 | AD58: NA | AE58: 0 | AF58: 0 | AG58: 0 | AH58: NA | AI58: 0 | AJ58: 0 | AK58: 0 | AL58: NA | AM58: 0 | AN58: 0 | AO58: 0 | AP58: NA | AQ58: 0 | AR58: 0 | AS58: 0 | AT58: NA | AU58: 0 | AV58: 0 | AW58: 0 | AX58: NA | AY58: 0 | AZ58: 0 | BA58: 0 | BB58: IMPORTACIONES RUBI S.A. | BC58: 1000417193 | BD58: REGULAR_OMD_PR
A59: 58 | B59: W/M | C59: PE000820001B | D59: WD12BVC2S6C.ABLGLGP | E59: 20220630 | F59: 01-F001-00242598 | G59: 2022W26 | H59: PEN | I59: 15 | J59: 1600.93 | K59: 24013.95 | L59: 3.788 | M59: 1600.93 | N59: NA | O59: 0 | P59: 0 | Q59: 0 | R59: NA | S59: 0 | T59: 0 | U59: 0 | V59: NA | W59: 0 | X59: 0 | Y59: 0 | Z59: NA | AA59: 0 | AB59: 0 | AC59: 0 | AD59: NA | AE59: 0 | AF59: 0 | AG59: 0 | AH59: NA | AI59: 0 | AJ59: 0 | AK59: 0 | AL59: NA | AM59: 0 | AN59: 0 | AO59: 0 | AP59: NA | AQ59: 0 | AR59: 0 | AS59: 0 | AT59: NA | AU59: 0 | AV59: 0 | AW59: 0 | AX59: NA | AY59: 0 | AZ59: 0 | BA59: 0 | BB59: IMPORTACIONES RUBI S.A. | BC59: 1000417193 | BD59: REGULAR_OMD_PR
A60: 59 | B60: W/M | C60: PE000820001B | D60: WD12BVC2S6C.ABLGLGP | E60: 20220615 | F60: 01-F001-00241439 | G60: 2022W22 | H60: PEN | I60: 10 | J60: 1600.93 | K60: 16009.3 | L60: 3.759 | M60: 1600.93 | N60: NA | O60: 0 | P60: 0 | Q60: 0 | R60: NA | S60: 0 | T60: 0 | U60: 0 | V60: NA | W60: 0 | X60: 0 | Y60: 0 | Z60: NA | AA60: 0 | AB60: 0 | AC60: 0 | AD60: NA | AE60: 0 | AF60: 0 | AG60: 0 | AH60: NA | AI60: 0 | AJ60: 0 | AK60: 0 | AL60: NA | AM60: 0 | AN60: 0 | AO60: 0 | AP60: NA | AQ60: 0 | AR60: 0 | AS60: 0 | AT60: NA | AU60: 0 | AV60: 0 | AW60: 0 | AX60: NA | AY60: 0 | AZ60: 0 | BA60: 0 | BB60: IMPORTACIONES RUBI S.A. | BC60: 1000416423 | BD60: REGULAR_OMD_PR
A61: 60 | B61: W/M | C61: PE000820001B | D61: WD12BVC2S6C.ABLGLGP | E61: 20211222 | G61: 2021W50 | H61: PEN | I61: 2 | J61: 2058.56 | K61: 4117.12 | L61: 4.055 | M61: 2058.56 | N61: NA | O61: 0 | P61: 0 | Q61: 0 | R61: NA | S61: 0 | T61: 0 | U61: 0 | V61: NA | W61: 0 | X61: 0 | Y61: 0 | Z61: NA | AA61: 0 | AB61: 0 | AC61: 0 | AD61: NA | AE61: 0 | AF61: 0 | AG61: 0 | AH61: NA | AI61: 0 | AJ61: 0 | AK61: 0 | AL61: NA | AM61: 0 | AN61: 0 | AO61: 0 | AP61: NA | AQ61: 0 | AR61: 0 | AS61: 0 | AT61: NA | AU61: 0 | AV61: 0 | AW61: 0 | AX61: NA | AY61: 0 | AZ61: 0 | BA61: 0 | BB61: IMPORTACIONES RUBI S.A. | BC61: 1000411402 | BD61: REGULAR_OMD_PR
A62: 61 | B62: W/M | C62: PE000820001B | D62: WD12BVC2S6C.ABLGLGP | E62: 20211119 | F62: 01-F001-00229466 | G62: 2021W45 | H62: PEN | I62: 5 | J62: 2134.83 | K62: 10674.15 | L62: 4.02 | M62: 2134.83 | N62: NA | O62: 0 | P62: 0 | Q62: 0 | R62: NA | S62: 0 | T62: 0 | U62: 0 | V62: NA | W62: 0 | X62: 0 | Y62: 0 | Z62: NA | AA62: 0 | AB62: 0 | AC62: 0 | AD62: NA | AE62: 0 | AF62: 0 | AG62: 0 | AH62: NA | AI62: 0 | AJ62: 0 | AK62: 0 | AL62: NA | AM62: 0 | AN62: 0 | AO62: 0 | AP62: NA | AQ62: 0 | AR62: 0 | AS62: 0 | AT62: NA | AU62: 0 | AV62: 0 | AW62: 0 | AX62: NA | AY62: 0 | AZ62: 0 | BA62: 0 | BB62: IMPORTACIONES RUBI S.A. | BC62: 1000410565 | BD62: REGULAR_OMD_PR
A63: 62 | B63: W/M | C63: PE000820001B | D63: WD14BVC2S6C.ABLGLGP | E63: 20230927 | F63: 01-F001-00262803 | G63: 2023W39 | H63: PEN | I63: 40 | J63: 2287.37 | K63: 91494.8 | L63: 3.787 | M63: 2287.37 | N63: 6 | O63: 2287.37 | P63: 4 | Q63: 39 | R63: NA | S63: 0 | T63: 0 | U63: 0 | V63: NA | W63: 0 | X63: 0 | Y63: 0 | Z63: NA | AA63: 0 | AB63: 0 | AC63: 0 | AD63: NA | AE63: 0 | AF63: 0 | AG63: 0 | AH63: NA | AI63: 0 | AJ63: 0 | AK63: 0 | AL63: NA | AM63: 0 | AN63: 0 | AO63: 0 | AP63: NA | AQ63: 0 | AR63: 0 | AS63: 0 | AT63: NA | AU63: 0 | AV63: 0 | AW63: 0 | AX63: NA | AY63: 0 | AZ63: 0 | BA63: 0 | BB63: IMPORTACIONES RUBI S.A. | BC63: 1000432743 | BD63: REGULAR_OMD_PR
A64: 63 | B64: W/M | C64: PE000820001B | D64: WD14BVC2S6C.ABLGLGP | E64: 20220521 | G64: 2022W17 | H64: PEN | I64: 3 | J64: 2287.37 | K64: 6862.11 | L64: 3.738 | M64: 2287.37 | N64: NA | O64: 0 | P64: 0 | Q64: 0 | R64: NA | S64: 0 | T64: 0 | U64: 0 | V64: NA | W64: 0 | X64: 0 | Y64: 0 | Z64: NA | AA64: 0 | AB64: 0 | AC64: 0 | AD64: NA | AE64: 0 | AF64: 0 | AG64: 0 | AH64: NA | AI64: 0 | AJ64: 0 | AK64: 0 | AL64: NA | AM64: 0 | AN64: 0 | AO64: 0 | AP64: NA | AQ64: 0 | AR64: 0 | AS64: 0 | AT64: NA | AU64: 0 | AV64: 0 | AW64: 0 | AX64: NA | AY64: 0 | AZ64: 0 | BA64: 0 | BB64: IMPORTACIONES RUBI S.A. | BC64: 1000415663 | BD64: REGULAR_OMD_PR
A65: 64 | B65: W/M | C65: PE000820001B | D65: WD14BVC2S6C.ABLGLGP | E65: 20220505 | G65: 2022W17 | H65: PEN | I65: 2 | J65: 2287.37 | K65: 4574.74 | L65: 3.805 | M65: 2287.37 | N65: NA | O65: 0 | P65: 0 | Q65: 0 | R65: NA | S65: 0 | T65: 0 | U65: 0 | V65: NA | W65: 0 | X65: 0 | Y65: 0 | Z65: NA | AA65: 0 | AB65: 0 | AC65: 0 | AD65: NA | AE65: 0 | AF65: 0 | AG65: 0 | AH65: NA | AI65: 0 | AJ65: 0 | AK65: 0 | AL65: NA | AM65: 0 | AN65: 0 | AO65: 0 | AP65: NA | AQ65: 0 | AR65: 0 | AS65: 0 | AT65: NA | AU65: 0 | AV65: 0 | AW65: 0 | AX65: NA | AY65: 0 | AZ65: 0 | BA65: 0 | BB65: IMPORTACIONES RUBI S.A. | BC65: 1000415663 | BD65: REGULAR_OMD_PR
A66: 65 | B66: W/M | C66: PE000820001B | D66: WD14BVC2S6C.ABLGLGP | E66: 20220429 | G66: 2022W17 | H66: PEN | I66: 5 | J66: 2287.37 | K66: 11436.85 | L66: 3.852 | M66: 2287.37 | N66: NA | O66: 0 | P66: 0 | Q66: 0 | R66: NA | S66: 0 | T66: 0 | U66: 0 | V66: NA | W66: 0 | X66: 0 | Y66: 0 | Z66: NA | AA66: 0 | AB66: 0 | AC66: 0 | AD66: NA | AE66: 0 | AF66: 0 | AG66: 0 | AH66: NA | AI66: 0 | AJ66: 0 | AK66: 0 | AL66: NA | AM66: 0 | AN66: 0 | AO66: 0 | AP66: NA | AQ66: 0 | AR66: 0 | AS66: 0 | AT66: NA | AU66: 0 | AV66: 0 | AW66: 0 | AX66: NA | AY66: 0 | AZ66: 0 | BA66: 0 | BB66: IMPORTACIONES RUBI S.A. | BC66: 1000415611 | BD66: REGULAR_OMD_PR
A67: 66 | B67: W/M | C67: PE000820001B | D67: WD14BVC2S6C.ABLGLGP | E67: 20211009 | G67: 2021W40 | H67: PEN | I67: 5 | J67: 2134.83 | K67: 10674.15 | L67: 4.109 | M67: 2134.83 | N67: NA | O67: 0 | P67: 0 | Q67: 0 | R67: NA | S67: 0 | T67: 0 | U67: 0 | V67: NA | W67: 0 | X67: 0 | Y67: 0 | Z67: NA | AA67: 0 | AB67: 0 | AC67: 0 | AD67: NA | AE67: 0 | AF67: 0 | AG67: 0 | AH67: NA | AI67: 0 | AJ67: 0 | AK67: 0 | AL67: NA | AM67: 0 | AN67: 0 | AO67: 0 | AP67: NA | AQ67: 0 | AR67: 0 | AS67: 0 | AT67: NA | AU67: 0 | AV67: 0 | AW67: 0 | AX67: NA | AY67: 0 | AZ67: 0 | BA67: 0 | BB67: IMPORTACIONES RUBI S.A. | BC67: 1000409357 | BD67: REGULAR_OMD_PR
A68: 67 | B68: W/M | C68: PE000820001B | D68: WD14BVC2S6C.ABLGLGP | E68: 20210625 | G68: 2021W24 | H68: PEN | I68: 8 | J68: 2058.56 | K68: 16468.48 | L68: 3.988 | M68: 2058.56 | N68: NA | O68: 0 | P68: 0 | Q68: 0 | R68: NA | S68: 0 | T68: 0 | U68: 0 | V68: NA | W68: 0 | X68: 0 | Y68: 0 | Z68: NA | AA68: 0 | AB68: 0 | AC68: 0 | AD68: NA | AE68: 0 | AF68: 0 | AG68: 0 | AH68: NA | AI68: 0 | AJ68: 0 | AK68: 0 | AL68: NA | AM68: 0 | AN68: 0 | AO68: 0 | AP68: NA | AQ68: 0 | AR68: 0 | AS68: 0 | AT68: NA | AU68: 0 | AV68: 0 | AW68: 0 | AX68: NA | AY68: 0 | AZ68: 0 | BA68: 0 | BB68: IMPORTACIONES RUBI S.A. | BC68: 1000406705 | BD68: REGULAR_OMD_PR
A69: 68 | B69: W/M | C69: PE000820001B | D69: WD15EG2S.AESGLGP | E69: 20221031 | G69: 2022W43 | H69: PEN | I69: 40 | J69: 3393.31 | K69: 135732.4 | L69: 3.978 | M69: 3393.31 | N69: 7 | O69: 3393.31 | P69: 2 | Q69: 14 | R69: NA | S69: 0 | T69: 0 | U69: 0 | V69: NA | W69: 0 | X69: 0 | Y69: 0 | Z69: NA | AA69: 0 | AB69: 0 | AC69: 0 | AD69: NA | AE69: 0 | AF69: 0 | AG69: 0 | AH69: NA | AI69: 0 | AJ69: 0 | AK69: 0 | AL69: NA | AM69: 0 | AN69: 0 | AO69: 0 | AP69: NA | AQ69: 0 | AR69: 0 | AS69: 0 | AT69: NA | AU69: 0 | AV69: 0 | AW69: 0 | AX69: NA | AY69: 0 | AZ69: 0 | BA69: 0 | BB69: IMPORTACIONES RUBI S.A. | BC69: 1000420826 | BD69: REGULAR_OMD_PR
A70: 69 | B70: W/M | C70: PE000820001B | D70: WD15EG2S.AESGLGP | E70: 20220630 | F70: 01-F001-00242602 | G70: 2022W26 | H70: PEN | I70: 25 | J70: 2439.92 | K70: 60998 | L70: 3.788 | M70: 2439.92 | N70: NA | O70: 0 | P70: 0 | Q70: 0 | R70: NA | S70: 0 | T70: 0 | U70: 0 | V70: NA | W70: 0 | X70: 0 | Y70: 0 | Z70: NA | AA70: 0 | AB70: 0 | AC70: 0 | AD70: NA | AE70: 0 | AF70: 0 | AG70: 0 | AH70: NA | AI70: 0 | AJ70: 0 | AK70: 0 | AL70: NA | AM70: 0 | AN70: 0 | AO70: 0 | AP70: NA | AQ70: 0 | AR70: 0 | AS70: 0 | AT70: NA | AU70: 0 | AV70: 0 | AW70: 0 | AX70: NA | AY70: 0 | AZ70: 0 | BA70: 0 | BB70: IMPORTACIONES RUBI S.A. | BC70: 1000417193 | BD70: REGULAR_OMD_PR
A71: 70 | B71: W/M | C71: PE000820001B | D71: WD15EG2S.AESGLGP | E71: 20211119 | F71: 01-F001-00229466 | G71: 2021W45 | H71: PEN | I71: 2 | J71: 2897.54 | K71: 5795.08 | L71: 4.02 | M71: 2897.54 | N71: NA | O71: 0 | P71: 0 | Q71: 0 | R71: NA | S71: 0 | T71: 0 | U71: 0 | V71: NA | W71: 0 | X71: 0 | Y71: 0 | Z71: NA | AA71: 0 | AB71: 0 | AC71: 0 | AD71: NA | AE71: 0 | AF71: 0 | AG71: 0 | AH71: NA | AI71: 0 | AJ71: 0 | AK71: 0 | AL71: NA | AM71: 0 | AN71: 0 | AO71: 0 | AP71: NA | AQ71: 0 | AR71: 0 | AS71: 0 | AT71: NA | AU71: 0 | AV71: 0 | AW71: 0 | AX71: NA | AY71: 0 | AZ71: 0 | BA71: 0 | BB71: IMPORTACIONES RUBI S.A. | BC71: 1000410565 | BD71: REGULAR_OMD_PR
A72: 71 | B72: W/M | C72: PE000820001B | D72: WD15EG2S.AESGLGP | E72: 20210624 | F72: 01-F001-00219586 | G72: 2021W24 | H72: PEN | I72: 2 | J72: 2706.86 | K72: 5413.72 | L72: 3.981 | M72: 2706.86 | N72: NA | O72: 0 | P72: 0 | Q72: 0 | R72: NA | S72: 0 | T72: 0 | U72: 0 | V72: NA | W72: 0 | X72: 0 | Y72: 0 | Z72: NA | AA72: 0 | AB72: 0 | AC72: 0 | AD72: NA | AE72: 0 | AF72: 0 | AG72: 0 | AH72: NA | AI72: 0 | AJ72: 0 | AK72: 0 | AL72: NA | AM72: 0 | AN72: 0 | AO72: 0 | AP72: NA | AQ72: 0 | AR72: 0 | AS72: 0 | AT72: NA | AU72: 0 | AV72: 0 | AW72: 0 | AX72: NA | AY72: 0 | AZ72: 0 | BA72: 0 | BB72: IMPORTACIONES RUBI S.A. | BC72: 1000406694 | BD72: REGULAR_OMD_PR
A73: 72 | B73: W/M | C73: PE000820001B | D73: WT13BPBK.ABMGLGP | E73: 20240125 | F73: 01-F001-00268198 | G73: 2024W04 | H73: PEN | I73: 62 | J73: 990.76 | K73: 61427.12 | L73: 3.76 | M73: 990.76 | N73: 9 | O73: 990.76 | P73: 7 | Q73: 62 | R73: NA | S73: 0 | T73: 0 | U73: 0 | V73: NA | W73: 0 | X73: 0 | Y73: 0 | Z73: NA | AA73: 0 | AB73: 0 | AC73: 0 | AD73: NA | AE73: 0 | AF73: 0 | AG73: 0 | AH73: NA | AI73: 0 | AJ73: 0 | AK73: 0 | AL73: NA | AM73: 0 | AN73: 0 | AO73: 0 | AP73: NA | AQ73: 0 | AR73: 0 | AS73: 0 | AT73: NA | AU73: 0 | AV73: 0 | AW73: 0 | AX73: NA | AY73: 0 | AZ73: 0 | BA73: 0 | BB73: IMPORTACIONES RUBI S.A. | BC73: 1000438257 | BD73: REGULAR_OMD_PR
A74: 73 | B74: W/M | C74: PE000820001B | D74: WT13BPBK.ABMGLGP | E74: 20240125 | F74: 01-F001-00268186 | G74: 2024W04 | H74: PEN | I74: 52 | J74: 990.76 | K74: 51519.52 | L74: 3.76 | M74: 990.76 | N74: 9 | O74: 990.76 | P74: 39 | Q74: 39 | R74: NA | S74: 0 | T74: 0 | U74: 0 | V74: NA | W74: 0 | X74: 0 | Y74: 0 | Z74: NA | AA74: 0 | AB74: 0 | AC74: 0 | AD74: NA | AE74: 0 | AF74: 0 | AG74: 0 | AH74: NA | AI74: 0 | AJ74: 0 | AK74: 0 | AL74: NA | AM74: 0 | AN74: 0 | AO74: 0 | AP74: NA | AQ74: 0 | AR74: 0 | AS74: 0 | AT74: NA | AU74: 0 | AV74: 0 | AW74: 0 | AX74: NA | AY74: 0 | AZ74: 0 | BA74: 0 | BB74: IMPORTACIONES RUBI S.A. | BC74: 1000438257 | BD74: REGULAR_OMD_PR
A75: 74 | B75: W/M | C75: PE000820001B | D75: WT13BPBK.ABMGLGP | E75: 20231207 | G75: 2023W48 | H75: PEN | I75: 57 | J75: 1067.03 | K75: 60820.71 | L75: 3.757 | M75: 1067.03 | N75: NA | O75: 0 | P75: 0 | Q75: 0 | R75: NA | S75: 0 | T75: 0 | U75: 0 | V75: NA | W75: 0 | X75: 0 | Y75: 0 | Z75: NA | AA75: 0 | AB75: 0 | AC75: 0 | AD75: NA | AE75: 0 | AF75: 0 | AG75: 0 | AH75: NA | AI75: 0 | AJ75: 0 | AK75: 0 | AL75: NA | AM75: 0 | AN75: 0 | AO75: 0 | AP75: NA | AQ75: 0 | AR75: 0 | AS75: 0 | AT75: NA | AU75: 0 | AV75: 0 | AW75: 0 | AX75: NA | AY75: 0 | AZ75: 0 | BA75: 0 | BB75: IMPORTACIONES RUBI S.A. | BC75: 1000435628 | BD75: REGULAR_OMD_PR
A76: 75 | B76: W/M | C76: PE000820001B | D76: WT13BPBK.ABMGLGP | E76: 20231207 | G76: 2023W48 | H76: PEN | I76: 57 | J76: 1067.03 | K76: 60820.71 | L76: 3.757 | M76: 1067.03 | N76: NA | O76: 0 | P76: 0 | Q76: 0 | R76: NA | S76: 0 | T76: 0 | U76: 0 | V76: NA | W76: 0 | X76: 0 | Y76: 0 | Z76: NA | AA76: 0 | AB76: 0 | AC76: 0 | AD76: NA | AE76: 0 | AF76: 0 | AG76: 0 | AH76: NA | AI76: 0 | AJ76: 0 | AK76: 0 | AL76: NA | AM76: 0 | AN76: 0 | AO76: 0 | AP76: NA | AQ76: 0 | AR76: 0 | AS76: 0 | AT76: NA | AU76: 0 | AV76: 0 | AW76: 0 | AX76: NA | AY76: 0 | AZ76: 0 | BA76: 0 | BB76: IMPORTACIONES RUBI S.A. | BC76: 1000435628 | BD76: REGULAR_OMD_PR
A77: 76 | B77: W/M | C77: PE000820001B | D77: WT17BV6.ABMGLGP | E77: 20240227 | G77: 2024W08 | H77: PEN | I77: 65 | J77: 1295.85 | K77: 84230.25 | L77: 3.803 | M77: 1295.85 | N77: 10 | O77: 1295.85 | P77: 5 | Q77: 53 | R77: NA | S77: 0 | T77: 0 | U77: 0 | V77: NA | W77: 0 | X77: 0 | Y77: 0 | Z77: NA | AA77: 0 | AB77: 0 | AC77: 0 | AD77: NA | AE77: 0 | AF77: 0 | AG77: 0 | AH77: NA | AI77: 0 | AJ77: 0 | AK77: 0 | AL77: NA | AM77: 0 | AN77: 0 | AO77: 0 | AP77: NA | AQ77: 0 | AR77: 0 | AS77: 0 | AT77: NA | AU77: 0 | AV77: 0 | AW77: 0 | AX77: NA | AY77: 0 | AZ77: 0 | BA77: 0 | BB77: IMPORTACIONES RUBI S.A. | BC77: 1000439898 | BD77: REGULAR_OMD_PR
A78: 77 | B78: W/M | C78: PE000820001B | D78: WT17BV6.ABMGLGP | E78: 20240227 | G78: 2024W09 | H78: PEN | I78: -1 | J78: 1295.85 | K78: -1295.85 | L78: 3.803 | M78: 1295.85 | N78: NA | O78: 0 | P78: 0 | Q78: 0 | R78: NA | S78: 0 | T78: 0 | U78: 0 | V78: NA | W78: 0 | X78: 0 | Y78: 0 | Z78: NA | AA78: 0 | AB78: 0 | AC78: 0 | AD78: NA | AE78: 0 | AF78: 0 | AG78: 0 | AH78: NA | AI78: 0 | AJ78: 0 | AK78: 0 | AL78: NA | AM78: 0 | AN78: 0 | AO78: 0 | AP78: NA | AQ78: 0 | AR78: 0 | AS78: 0 | AT78: NA | AU78: 0 | AV78: 0 | AW78: 0 | AX78: NA | AY78: 0 | AZ78: 0 | BA78: 0 | BB78: IMPORTACIONES RUBI S.A. | BC78: 3000033065 | BD78: GOODSET_RETURN_OMD_PR
A79: 78 | B79: W/M | C79: PE000820001B | D79: WT17BV6.ABMGLGP | E79: 20240227 | F79: 01-F001-00269912 | G79: 2024W08 | H79: PEN | I79: 65 | J79: 1295.85 | K79: 84230.25 | L79: 3.803 | M79: 1295.85 | N79: 10 | O79: 1295.85 | Q79: 65 | R79: NA | S79: 0 | T79: 0 | U79: 0 | V79: NA | W79: 0 | X79: 0 | Y79: 0 | Z79: NA | AA79: 0 | AB79: 0 | AC79: 0 | AD79: NA | AE79: 0 | AF79: 0 | AG79: 0 | AH79: NA | AI79: 0 | AJ79: 0 | AK79: 0 | AL79: NA | AM79: 0 | AN79: 0 | AO79: 0 | AP79: NA | AQ79: 0 | AR79: 0 | AS79: 0 | AT79: NA | AU79: 0 | AV79: 0 | AW79: 0 | AX79: NA | AY79: 0 | AZ79: 0 | BA79: 0 | BB79: IMPORTACIONES RUBI S.A. | BC79: 1000439898 | BD79: REGULAR_OMD_PR
A80: 79 | B80: W/M | C80: PE000820001B | D80: WT17BV6.ABMGLGP | E80: 20240227 | F80: 01-F001-00269908 | G80: 2024W08 | H80: PEN | I80: 70 | J80: 1295.85 | K80: 90709.5 | L80: 3.803 | M80: 1295.85 | N80: 10 | O80: 1295.85 | Q80: 70 | R80: NA | S80: 0 | T80: 0 | U80: 0 | V80: NA | W80: 0 | X80: 0 | Y80: 0 | Z80: NA | AA80: 0 | AB80: 0 | AC80: 0 | AD80: NA | AE80: 0 | AF80: 0 | AG80: 0 | AH80: NA | AI80: 0 | AJ80: 0 | AK80: 0 | AL80: NA | AM80: 0 | AN80: 0 | AO80: 0 | AP80: NA | AQ80: 0 | AR80: 0 | AS80: 0 | AT80: NA | AU80: 0 | AV80: 0 | AW80: 0 | AX80: NA | AY80: 0 | AZ80: 0 | BA80: 0 | BB80: IMPORTACIONES RUBI S.A. | BC80: 1000439898 | BD80: REGULAR_OMD_PR
A81: 80 | B81: W/M | C81: PE000820001B | D81: WT17BV6.ABMGLGP | E81: 20240227 | F81: 01-F001-00269907 | G81: 2024W08 | H81: PEN | I81: 62 | J81: 1295.85 | K81: 80342.7 | L81: 3.803 | M81: 1295.85 | N81: 10 | O81: 1295.85 | Q81: 62 | R81: NA | S81: 0 | T81: 0 | U81: 0 | V81: NA | W81: 0 | X81: 0 | Y81: 0 | Z81: NA | AA81: 0 | AB81: 0 | AC81: 0 | AD81: NA | AE81: 0 | AF81: 0 | AG81: 0 | AH81: NA | AI81: 0 | AJ81: 0 | AK81: 0 | AL81: NA | AM81: 0 | AN81: 0 | AO81: 0 | AP81: NA | AQ81: 0 | AR81: 0 | AS81: 0 | AT81: NA | AU81: 0 | AV81: 0 | AW81: 0 | AX81: NA | AY81: 0 | AZ81: 0 | BA81: 0 | BB81: IMPORTACIONES RUBI S.A. | BC81: 1000439898 | BD81: REGULAR_OMD_PR
A82: 81 | B82: W/M | C82: PE000820001B | D82: WT17BV6.ABMGLGP | E82: 20240227 | F82: 01-F001-00269906 | G82: 2024W08 | H82: PEN | I82: 65 | J82: 1295.85 | K82: 84230.25 | L82: 3.803 | M82: 1295.85 | N82: 10 | O82: 1295.85 | Q82: 65 | R82: NA | S82: 0 | T82: 0 | U82: 0 | V82: NA | W82: 0 | X82: 0 | Y82: 0 | Z82: NA | AA82: 0 | AB82: 0 | AC82: 0 | AD82: NA | AE82: 0 | AF82: 0 | AG82: 0 | AH82: NA | AI82: 0 | AJ82: 0 | AK82: 0 | AL82: NA | AM82: 0 | AN82: 0 | AO82: 0 | AP82: NA | AQ82: 0 | AR82: 0 | AS82: 0 | AT82: NA | AU82: 0 | AV82: 0 | AW82: 0 | AX82: NA | AY82: 0 | AZ82: 0 | BA82: 0 | BB82: IMPORTACIONES RUBI S.A. | BC82: 1000439898 | BD82: REGULAR_OMD_PR
A83: 82 | B83: W/M | C83: PE000820001B | D83: WT17BV6.ABMGLGP | E83: 20240227 | F83: 01-F001-00269905 | G83: 2024W08 | H83: PEN | I83: 65 | J83: 1295.85 | K83: 84230.25 | L83: 3.803 | M83: 1295.85 | N83: 10 | O83: 1295.85 | Q83: 65 | R83: NA | S83: 0 | T83: 0 | U83: 0 | V83: NA | W83: 0 | X83: 0 | Y83: 0 | Z83: NA | AA83: 0 | AB83: 0 | AC83: 0 | AD83: NA | AE83: 0 | AF83: 0 | AG83: 0 | AH83: NA | AI83: 0 | AJ83: 0 | AK83: 0 | AL83: NA | AM83: 0 | AN83: 0 | AO83: 0 | AP83: NA | AQ83: 0 | AR83: 0 | AS83: 0 | AT83: NA | AU83: 0 | AV83: 0 | AW83: 0 | AX83: NA | AY83: 0 | AZ83: 0 | BA83: 0 | BB83: IMPORTACIONES RUBI S.A. | BC83: 1000439898 | BD83: REGULAR_OMD_PR
A84: 83 | B84: W/M | C84: PE000820001B | D84: WT17BV6.ABMGLGP | E84: 20240227 | F84: 01-F001-00269904 | G84: 2024W08 | H84: PEN | I84: 20 | J84: 1295.85 | K84: 25917 | L84: 3.803 | M84: 1295.85 | N84: 10 | O84: 1295.85 | Q84: 20 | R84: NA | S84: 0 | T84: 0 | U84: 0 | V84: NA | W84: 0 | X84: 0 | Y84: 0 | Z84: NA | AA84: 0 | AB84: 0 | AC84: 0 | AD84: NA | AE84: 0 | AF84: 0 | AG84: 0 | AH84: NA | AI84: 0 | AJ84: 0 | AK84: 0 | AL84: NA | AM84: 0 | AN84: 0 | AO84: 0 | AP84: NA | AQ84: 0 | AR84: 0 | AS84: 0 | AT84: NA | AU84: 0 | AV84: 0 | AW84: 0 | AX84: NA | AY84: 0 | AZ84: 0 | BA84: 0 | BB84: IMPORTACIONES RUBI S.A. | BC84: 1000439898 | BD84: REGULAR_OMD_PR
A85: 84 | B85: W/M | C85: PE000820001B | D85: WT17BV6.ABMGLGP | E85: 20240125 | F85: 01-F001-00268194 | G85: 2024W04 | H85: PEN | I85: 40 | J85: 1295.85 | K85: 51834 | L85: 3.76 | M85: 1295.85 | N85: NA | O85: 0 | P85: 0 | Q85: 0 | R85: NA | S85: 0 | T85: 0 | U85: 0 | V85: NA | W85: 0 | X85: 0 | Y85: 0 | Z85: NA | AA85: 0 | AB85: 0 | AC85: 0 | AD85: NA | AE85: 0 | AF85: 0 | AG85: 0 | AH85: NA | AI85: 0 | AJ85: 0 | AK85: 0 | AL85: NA | AM85: 0 | AN85: 0 | AO85: 0 | AP85: NA | AQ85: 0 | AR85: 0 | AS85: 0 | AT85: NA | AU85: 0 | AV85: 0 | AW85: 0 | AX85: NA | AY85: 0 | AZ85: 0 | BA85: 0 | BB85: IMPORTACIONES RUBI S.A. | BC85: 1000438233 | BD85: REGULAR_OMD_PR
A86: 85 | B86: W/M | C86: PE000820001B | D86: WT17BV6.ABMGLGP | E86: 20230524 | G86: 2023W20 | H86: PEN | I86: 10 | J86: 1524.66 | K86: 15246.6 | L86: 3.695 | M86: 1524.66 | N86: NA | O86: 0 | P86: 0 | Q86: 0 | R86: NA | S86: 0 | T86: 0 | U86: 0 | V86: NA | W86: 0 | X86: 0 | Y86: 0 | Z86: NA | AA86: 0 | AB86: 0 | AC86: 0 | AD86: NA | AE86: 0 | AF86: 0 | AG86: 0 | AH86: NA | AI86: 0 | AJ86: 0 | AK86: 0 | AL86: NA | AM86: 0 | AN86: 0 | AO86: 0 | AP86: NA | AQ86: 0 | AR86: 0 | AS86: 0 | AT86: NA | AU86: 0 | AV86: 0 | AW86: 0 | AX86: NA | AY86: 0 | AZ86: 0 | BA86: 0 | BB86: IMPORTACIONES RUBI S.A. | BC86: 1000427780 | BD86: REGULAR_OMD_PR
A87: 86 | B87: W/M | C87: PE000820001B | D87: WT19BPB.ABMGLGP | E87: 20240125 | F87: 01-F001-00268196 | G87: 2024W04 | H87: PEN | I87: 40 | J87: 1372.12 | K87: 54884.8 | L87: 3.76 | M87: 1372.12 | N87: 8 | O87: 1372.12 | P87: 28 | Q87: 29 | R87: NA | S87: 0 | T87: 0 | U87: 0 | V87: NA | W87: 0 | X87: 0 | Y87: 0 | Z87: NA | AA87: 0 | AB87: 0 | AC87: 0 | AD87: NA | AE87: 0 | AF87: 0 | AG87: 0 | AH87: NA | AI87: 0 | AJ87: 0 | AK87: 0 | AL87: NA | AM87: 0 | AN87: 0 | AO87: 0 | AP87: NA | AQ87: 0 | AR87: 0 | AS87: 0 | AT87: NA | AU87: 0 | AV87: 0 | AW87: 0 | AX87: NA | AY87: 0 | AZ87: 0 | BA87: 0 | BB87: IMPORTACIONES RUBI S.A. | BC87: 1000438233 | BD87: REGULAR_OMD_PR
A88: 87 | B88: W/M | C88: PE000820001B | D88: WT19BPB.ABMGLGP | E88: 20230929 | G88: 2023W39 | H88: PEN | I88: 10 | J88: 1372.12 | K88: 13721.2 | L88: 3.806 | M88: 1372.12 | N88: NA | O88: 0 | P88: 0 | Q88: 0 | R88: NA | S88: 0 | T88: 0 | U88: 0 | V88: NA | W88: 0 | X88: 0 | Y88: 0 | Z88: NA | AA88: 0 | AB88: 0 | AC88: 0 | AD88: NA | AE88: 0 | AF88: 0 | AG88: 0 | AH88: NA | AI88: 0 | AJ88: 0 | AK88: 0 | AL88: NA | AM88: 0 | AN88: 0 | AO88: 0 | AP88: NA | AQ88: 0 | AR88: 0 | AS88: 0 | AT88: NA | AU88: 0 | AV88: 0 | AW88: 0 | AX88: NA | AY88: 0 | AZ88: 0 | BA88: 0 | BB88: IMPORTACIONES RUBI S.A. | BC88: 1000432887 | BD88: REGULAR_OMD_PR
A89: 88 | B89: W/M | C89: PE000820001B | D89: WT19BPB.ABMGLGP | E89: 20230929 | G89: 2023W39 | H89: PEN | I89: 64 | J89: 1372.12 | K89: 87815.68 | L89: 3.806 | M89: 1372.12 | N89: NA | O89: 0 | P89: 0 | Q89: 0 | R89: NA | S89: 0 | T89: 0 | U89: 0 | V89: NA | W89: 0 | X89: 0 | Y89: 0 | Z89: NA | AA89: 0 | AB89: 0 | AC89: 0 | AD89: NA | AE89: 0 | AF89: 0 | AG89: 0 | AH89: NA | AI89: 0 | AJ89: 0 | AK89: 0 | AL89: NA | AM89: 0 | AN89: 0 | AO89: 0 | AP89: NA | AQ89: 0 | AR89: 0 | AS89: 0 | AT89: NA | AU89: 0 | AV89: 0 | AW89: 0 | AX89: NA | AY89: 0 | AZ89: 0 | BA89: 0 | BB89: IMPORTACIONES RUBI S.A. | BC89: 1000432887 | BD89: REGULAR_OMD_PR
A90: 89 | B90: W/M | C90: PE000820001B | D90: WT19BPB.ABMGLGP | E90: 20230929 | G90: 2023W39 | H90: PEN | I90: 65 | J90: 1372.12 | K90: 89187.8 | L90: 3.806 | M90: 1372.12 | N90: NA | O90: 0 | P90: 0 | Q90: 0 | R90: NA | S90: 0 | T90: 0 | U90: 0 | V90: NA | W90: 0 | X90: 0 | Y90: 0 | Z90: NA | AA90: 0 | AB90: 0 | AC90: 0 | AD90: NA | AE90: 0 | AF90: 0 | AG90: 0 | AH90: NA | AI90: 0 | AJ90: 0 | AK90: 0 | AL90: NA | AM90: 0 | AN90: 0 | AO90: 0 | AP90: NA | AQ90: 0 | AR90: 0 | AS90: 0 | AT90: NA | AU90: 0 | AV90: 0 | AW90: 0 | AX90: NA | AY90: 0 | AZ90: 0 | BA90: 0 | BB90: IMPORTACIONES RUBI S.A. | BC90: 1000432887 | BD90: REGULAR_OMD_PR
A91: 90 | B91: W/M | C91: PE000820001B | D91: WT19BPB.ABMGLGP | E91: 20230929 | G91: 2023W39 | H91: PEN | I91: 65 | J91: 1372.12 | K91: 89187.8 | L91: 3.806 | M91: 1372.12 | N91: NA | O91: 0 | P91: 0 | Q91: 0 | R91: NA | S91: 0 | T91: 0 | U91: 0 | V91: NA | W91: 0 | X91: 0 | Y91: 0 | Z91: NA | AA91: 0 | AB91: 0 | AC91: 0 | AD91: NA | AE91: 0 | AF91: 0 | AG91: 0 | AH91: NA | AI91: 0 | AJ91: 0 | AK91: 0 | AL91: NA | AM91: 0 | AN91: 0 | AO91: 0 | AP91: NA | AQ91: 0 | AR91: 0 | AS91: 0 | AT91: NA | AU91: 0 | AV91: 0 | AW91: 0 | AX91: NA | AY91: 0 | AZ91: 0 | BA91: 0 | BB91: IMPORTACIONES RUBI S.A. | BC91: 1000432887 | BD91: REGULAR_OMD_PR
A92: 91 | B92: W/M | C92: PE000820001B | D92: WT19BPB.ABMGLGP | E92: 20230315 | G92: 2023W02 | H92: PEN | I92: 3 | J92: 1410.25 | K92: 4230.75 | L92: 3.789 | M92: 1410.25 | N92: NA | O92: 0 | P92: 0 | Q92: 0 | R92: NA | S92: 0 | T92: 0 | U92: 0 | V92: NA | W92: 0 | X92: 0 | Y92: 0 | Z92: NA | AA92: 0 | AB92: 0 | AC92: 0 | AD92: NA | AE92: 0 | AF92: 0 | AG92: 0 | AH92: NA | AI92: 0 | AJ92: 0 | AK92: 0 | AL92: NA | AM92: 0 | AN92: 0 | AO92: 0 | AP92: NA | AQ92: 0 | AR92: 0 | AS92: 0 | AT92: NA | AU92: 0 | AV92: 0 | AW92: 0 | AX92: NA | AY92: 0 | AZ92: 0 | BA92: 0 | BB92: IMPORTACIONES RUBI S.A. | BC92: 1000422908 | BD92: REGULAR_OMD_PR
A93: 92 | B93: W/M | C93: PE000820001B | D93: WT19BPB.ABMGLGP | E93: 20230309 | G93: 2023W02 | H93: PEN | I93: 4 | J93: 1410.25 | K93: 5641 | L93: 3.788 | M93: 1410.25 | N93: NA | O93: 0 | P93: 0 | Q93: 0 | R93: NA | S93: 0 | T93: 0 | U93: 0 | V93: NA | W93: 0 | X93: 0 | Y93: 0 | Z93: NA | AA93: 0 | AB93: 0 | AC93: 0 | AD93: NA | AE93: 0 | AF93: 0 | AG93: 0 | AH93: NA | AI93: 0 | AJ93: 0 | AK93: 0 | AL93: NA | AM93: 0 | AN93: 0 | AO93: 0 | AP93: NA | AQ93: 0 | AR93: 0 | AS93: 0 | AT93: NA | AU93: 0 | AV93: 0 | AW93: 0 | AX93: NA | AY93: 0 | AZ93: 0 | BA93: 0 | BB93: IMPORTACIONES RUBI S.A. | BC93: 1000422908 | BD93: REGULAR_OMD_PR
A94: 93 | B94: W/M | C94: PE000820001B | D94: WT19BPB.ABMGLGP | E94: 20230228 | F94: 01-F001-00252781 | G94: 2023W02 | H94: PEN | I94: 30 | J94: 1410.25 | K94: 42307.5 | L94: 3.816 | M94: 1410.25 | N94: NA | O94: 0 | P94: 0 | Q94: 0 | R94: NA | S94: 0 | T94: 0 | U94: 0 | V94: NA | W94: 0 | X94: 0 | Y94: 0 | Z94: NA | AA94: 0 | AB94: 0 | AC94: 0 | AD94: NA | AE94: 0 | AF94: 0 | AG94: 0 | AH94: NA | AI94: 0 | AJ94: 0 | AK94: 0 | AL94: NA | AM94: 0 | AN94: 0 | AO94: 0 | AP94: NA | AQ94: 0 | AR94: 0 | AS94: 0 | AT94: NA | AU94: 0 | AV94: 0 | AW94: 0 | AX94: NA | AY94: 0 | AZ94: 0 | BA94: 0 | BB94: IMPORTACIONES RUBI S.A. | BC94: 1000422908 | BD94: REGULAR_OMD_PR
A95: 94 | B95: W/M | C95: PE000820001B | D95: WT19BPB.ABMGLGP | E95: 20230228 | F95: 01-F001-00252781 | G95: 2023W02 | H95: PEN | I95: 13 | J95: 1410.25 | K95: 18333.25 | L95: 3.816 | M95: 1410.25 | N95: NA | O95: 0 | P95: 0 | Q95: 0 | R95: NA | S95: 0 | T95: 0 | U95: 0 | V95: NA | W95: 0 | X95: 0 | Y95: 0 | Z95: NA | AA95: 0 | AB95: 0 | AC95: 0 | AD95: NA | AE95: 0 | AF95: 0 | AG95: 0 | AH95: NA | AI95: 0 | AJ95: 0 | AK95: 0 | AL95: NA | AM95: 0 | AN95: 0 | AO95: 0 | AP95: NA | AQ95: 0 | AR95: 0 | AS95: 0 | AT95: NA | AU95: 0 | AV95: 0 | AW95: 0 | AX95: NA | AY95: 0 | AZ95: 0 | BA95: 0 | BB95: IMPORTACIONES RUBI S.A. | BC95: 1000422908 | BD95: REGULAR_OMD_PR
A96: 95 | B96: W/M | C96: PE000820001B | D96: WT19BPB.ABMGLGP | E96: 20230225 | F96: 01-F001-00252571 | G96: 2023W08 | H96: PEN | I96: 19 | J96: 1410.25 | K96: 26794.75 | L96: 3.82 | M96: 1410.25 | N96: NA | O96: 0 | P96: 0 | Q96: 0 | R96: NA | S96: 0 | T96: 0 | U96: 0 | V96: NA | W96: 0 | X96: 0 | Y96: 0 | Z96: NA | AA96: 0 | AB96: 0 | AC96: 0 | AD96: NA | AE96: 0 | AF96: 0 | AG96: 0 | AH96: NA | AI96: 0 | AJ96: 0 | AK96: 0 | AL96: NA | AM96: 0 | AN96: 0 | AO96: 0 | AP96: NA | AQ96: 0 | AR96: 0 | AS96: 0 | AT96: NA | AU96: 0 | AV96: 0 | AW96: 0 | AX96: NA | AY96: 0 | AZ96: 0 | BA96: 0 | BB96: IMPORTACIONES RUBI S.A. | BC96: 1000424246 | BD96: REGULAR_OMD_PR
A97: 96 | B97: W/M | C97: PE000820001B | D97: WT19BPB.ABMGLGP | E97: 20220930 | G97: 2022W39 | H97: PEN | I97: 50 | J97: 1410.25 | K97: 70512.5 | L97: 3.971 | M97: 1410.25 | N97: NA | O97: 0 | P97: 0 | Q97: 0 | R97: NA | S97: 0 | T97: 0 | U97: 0 | V97: NA | W97: 0 | X97: 0 | Y97: 0 | Z97: NA | AA97: 0 | AB97: 0 | AC97: 0 | AD97: NA | AE97: 0 | AF97: 0 | AG97: 0 | AH97: NA | AI97: 0 | AJ97: 0 | AK97: 0 | AL97: NA | AM97: 0 | AN97: 0 | AO97: 0 | AP97: NA | AQ97: 0 | AR97: 0 | AS97: 0 | AT97: NA | AU97: 0 | AV97: 0 | AW97: 0 | AX97: NA | AY97: 0 | AZ97: 0 | BA97: 0 | BB97: IMPORTACIONES RUBI S.A. | BC97: 1000419825 | BD97: REGULAR_OMD_PR

Sheet MIX_DETAIL
A1: CUSTOMER | B1: MODEL | C1: LINE SEQ | D1: LIQ START DATE | E1: LIQ END DATE | F1: LIQ QTY | G1: LIQ COST | H1: LIQ NEW COST | I1: DIFF | J1: REF LINE SEQ | K1: REF START DATE | L1: REF END DATE | M1: REF LIQ QTY | N1: REF COST | O1: REF NEW COST | P1: REF DIFF | Q1: ADJ START DATE | R1: ADJ END DATE | S1: ADJ LIQ QTY | T1: CUSTOMER QTY | U1: ADJ COST | V1: ADJ NEW COST | W1: ADJ DIFF | X1: ADJ AMOUNT
D2: 45411.701 | E2: 45411.701 | F2: 0 | G2: 0 | H2: 0 | I2: 0 | K2: 45411.701 | L2: 45411.701 | M2: 0 | N2: 0 | O2: 0 | P2: 0 | Q2: 45411.701 | R2: 45411.701 | S2: 0 | T2: 0 | U2: 0 | V2: 0 | W2: 0 | X2: 0

Sheet SPMS
A1: Promotion No | B1: Promotion Name | C1: Promotion Status Code | D1: Approved Date | E1: Promotion Start YYYYMMDD | F1: Promotion End YYYYMMDD | G1: Requestor Name | H1: Transaction Currency Code | I1: Promotion Property | J1: Subsidiary Dff1 | K1: Subsidiary Dff2 | L1: Subsidiary Dff3 | M1: Subsidiary Dff4 | N1: Subsidiary Dff5 | O1: Subsidiary Dff6 | P1: Line No | Q1: Budget Check Signal | R1: Promotion Line Status Code | S1: Sales PGM Reason Code | T1: Sales PGM Reason Name | U1: Sales PGM Type | V1: Customer Type | W1: Customer Code | X1: Customer Name | Y1: Product Type | Z1: Product Code | AA1: Division Code | AB1: Division Name | AC1: Calculation Method | AD1: Dc Operand | AE1: Expected Qty | AF1: Expected Cost | AG1: Sales PGM Status | AH1: Sales PGM Name | AI1: Sales PGM NO | AJ1: Sales PGM Product Code | AK1: Sales PGM Product Type | AL1: Offer Dc Operand | AM1: Offer Expected Qty | AN1: Offer Expected Cost | AO1: Sales PGM Approved YYYYMM | AP1: Sales PGM Approved YYYYMMDD | AQ1: Line Remark | AR1: Promotion Price | AS1: New Margin | AT1: Bundle Model Code | AU1: Limit Qty | AV1: Bundle Cost Rate | AW1: Cancel Flag
A2: PR-NTSO-20240327-0059 | B2: 2024 - RUBI - W/M - 20240403 AL 20240430 | C2: APPROVED | D2: 45378.761 | E2: 20240403 | F2: 20240430 | G2: Castillo Jose | H2: PEN | I2: NTTSO | K2: ALL | P2: 1 | Q2: G | R2: APPROVED | S2: TM_Z02 | T2: Sell out Support Rebate | U2: LUMPSUM | V2: Bill To | W2: PE000820001B | X2: IMPORTACIONES RUBI S.A. | Y2: Model | Z2: WD12BVC2S6C.ABLGLGP | AA2: DFT | AB2: W/M | AC2: AMT | AD2: 678.82 | AE2: 10 | AF2: 6788.2 | AJ2: WD12BVC2S6C.ABLGLGP | AK2: Model | AL2: 0 | AM2: 0 | AN2: 0 | AQ2: 2099_10__ | AR2: 2099 | AS2: 10 | AU2: 0 | AV2: N | AW2: N
A3: PR-NTSO-20240327-0059 | B3: 2024 - RUBI - W/M - 20240403 AL 20240430 | C3: APPROVED | D3: 45378.761 | E3: 20240403 | F3: 20240430 | G3: Castillo Jose | H3: PEN | I3: NTTSO | K3: ALL | P3: 2 | Q3: G | R3: APPROVED | S3: TM_Z02 | T3: Sell out Support Rebate | U3: LUMPSUM | V3: Bill To | W3: PE000820001B | X3: IMPORTACIONES RUBI S.A. | Y3: Model | Z3: WD14BVC2S6C.ABLGLGP | AA3: DFT | AB3: W/M | AC3: AMT | AD3: 152.54 | AE3: 14 | AF3: 2135.56 | AJ3: WD14BVC2S6C.ABLGLGP | AK3: Model | AL3: 0 | AM3: 0 | AN3: 0 | AQ3: 2799_10__ | AR3: 2799 | AS3: 10 | AU3: 0 | AV3: N | AW3: N
A4: PR-NTSO-20240327-0059 | B4: 2024 - RUBI - W/M - 20240403 AL 20240430 | C4: APPROVED | D4: 45378.761 | E4: 20240403 | F4: 20240430 | G4: Castillo Jose | H4: PEN | I4: NTTSO | K4: ALL | P4: 3 | Q4: G | R4: APPROVED | S4: TM_Z02 | T4: Sell out Support Rebate | U4: LUMPSUM | V4: Bill To | W4: PE000820001B | X4: IMPORTACIONES RUBI S.A. | Y4: Model | Z4: WD15EG2S.AESGLGP | AA4: DFT | AB4: W/M | AC4: AMT | AD4: 1144.07 | AE4: 7 | AF4: 8008.49 | AJ4: WD15EG2S.AESGLGP | AK4: Model | AL4: 0 | AM4: 0 | AN4: 0 | AQ4: 2949_10__ | AR4: 2949 | AS4: 10 | AU4: 0 | AV4: N | AW4: N
A5: PR-NTSO-20240327-0059 | B5: 2024 - RUBI - W/M - 20240403 AL 20240430 | C5: APPROVED | D5: 45378.761 | E5: 20240403 | F5: 20240430 | G5: Castillo Jose | H5: PEN | I5: NTTSO | K5: ALL | P5: 4 | Q5: G | R5: APPROVED | S5: TM_Z02 | T5: Sell out Support Rebate | U5: LUMPSUM | V5: Bill To | W5: PE000820001B | X5: IMPORTACIONES RUBI S.A. | Y5: Model | Z5: WT19BPB.ABMGLGP | AA5: DFT | AB5: W/M | AC5: AMT | AD5: 245.81 | AE5: 30 | AF5: 7374.3 | AJ5: WT19BPB.ABMGLGP | AK5: Model | AL5: 0 | AM5: 0 | AN5: 0 | AQ5: 1399_5__ | AR5: 1399 | AS5: 5 | AU5: 0 | AV5: N | AW5: N
A6: PR-NTSO-20240405-0031 | B6: 2024 - RUBI - Cooking - 20240410 AL 20240430 | C6: APPROVED | D6: 45387.632 | E6: 20240410 | F6: 20240430 | G6: Castillo Jose | H6: PEN | I6: NTTSO | K6: ALL | P6: 1 | Q6: G | R6: APPROVED | S6: TM_Z02 | T6: Sell out Support Rebate | U6: LUMPSUM | V6: Bill To | W6: PE000820001B | X6: IMPORTACIONES RUBI S.A. | Y6: Model | Z6: RSG314M.FSTGLPR | AA6: CVT | AB6: Cooking | AC6: AMT | AD6: 724.57 | AE6: 8 | AF6: 5796.56 | AJ6: RSG314M.FSTGLPR | AK6: Model | AL6: 0 | AM6: 0 | AN6: 0 | AQ6: 1599_10__8 | AR6: 1599 | AS6: 10 | AU6: 8 | AV6: N | AW6: N
A7: PR-NTSO-20240415-0011 | B7: 2024 - RUBI - Cooking - 20240420 AL 20240430 | C7: APPROVED | D7: 45398.44 | E7: 20240420 | F7: 20240430 | G7: Castillo Jose | H7: PEN | I7: NTTSO | K7: ALL | P7: 1 | Q7: G | R7: APPROVED | S7: TM_Z02 | T7: Sell out Support Rebate | U7: LUMPSUM | V7: Bill To | W7: PE000820001B | X7: IMPORTACIONES RUBI S.A. | Y7: Model | Z7: MS2596DIR.BBKGLPR | AA7: CVT | AB7: Cooking | AC7: AMT | AD7: 76.27 | AE7: 21 | AF7: 1601.67 | AJ7: MS2596DIR.BBKGLPR | AK7: Model | AL7: 0 | AM7: 0 | AN7: 0 | AQ7: 379_10__ | AR7: 379 | AS7: 10 | AU7: 0 | AV7: N | AW7: N
A8: PR-NTSO-20240416-0005 | B8: 2024 - RUBI - Cooking - 20240422 AL 20240430 | C8: APPROVED | D8: 45398.833 | E8: 20240422 | F8: 20240430 | G8: Castillo Jose | H8: PEN | I8: NTTSO | K8: ALL | P8: 1 | Q8: G | R8: APPROVED | S8: TM_Z02 | T8: Sell out Support Rebate | U8: LUMPSUM | V8: Bill To | W8: PE000820001B | X8: IMPORTACIONES RUBI S.A. | Y8: Model | Z8: MS4296DIR.BBKGLPR | AA8: CVT | AB8: Cooking | AC8: AMT | AD8: 7.63 | AE8: 140 | AF8: 1068.2 | AJ8: MS4296DIR.BBKGLPR | AK8: Model | AL8: 0 | AM8: 0 | AN8: 0 | AQ8: 539_10__ | AR8: 539 | AS8: 10 | AU8: 0 | AV8: N | AW8: N
A9: PR-NTSO-20240416-0005 | B9: 2024 - RUBI - Cooking - 20240422 AL 20240430 | C9: APPROVED | D9: 45398.833 | E9: 20240422 | F9: 20240430 | G9: Castillo Jose | H9: PEN | I9: NTTSO | K9: ALL | P9: 2 | Q9: G | R9: APPROVED | S9: TM_Z02 | T9: Sell out Support Rebate | U9: LUMPSUM | V9: Bill To | W9: PE000820001B | X9: IMPORTACIONES RUBI S.A. | Y9: Model | Z9: RSG314M.FSTGLPR | AA9: CVT | AB9: Cooking | AC9: AMT | AD9: 724.57 | AE9: 10 | AF9: 7245.7 | AJ9: RSG314M.FSTGLPR | AK9: Model | AL9: 0 | AM9: 0 | AN9: 0 | AQ9: 1599_10__ | AR9: 1599 | AS9: 10 | AU9: 0 | AV9: N | AW9: N
A10: PR-NTSO-20240416-0006 | B10: 2024 - RUBI - W/M - 20240422 AL 20240430 | C10: APPROVED | D10: 45398.833 | E10: 20240422 | F10: 20240430 | G10: Castillo Jose | H10: PEN | I10: NTTSO | K10: ALL | P10: 1 | Q10: G | R10: APPROVED | S10: TM_Z02 | T10: Sell out Support Rebate | U10: LUMPSUM | V10: Bill To | W10: PE000820001B | X10: IMPORTACIONES RUBI S.A. | Y10: Model | Z10: WT13BPBK.ABMGLGP | AA10: DFT | AB10: W/M | AC10: AMT | AD10: 76.27 | AE10: 40 | AF10: 3050.8 | AJ10: WT13BPBK.ABMGLGP | AK10: Model | AL10: 0 | AM10: 0 | AN10: 0 | AQ10: 1199_10__ | AR10: 1199 | AS10: 10 | AU10: 0 | AV10: N | AW10: N
A11: PR-NTSO-20240416-0006 | B11: 2024 - RUBI - W/M - 20240422 AL 20240430 | C11: APPROVED | D11: 45398.833 | E11: 20240422 | F11: 20240430 | G11: Castillo Jose | H11: PEN | I11: NTTSO | K11: ALL | P11: 2 | Q11: G | R11: APPROVED | S11: TM_Z02 | T11: Sell out Support Rebate | U11: LUMPSUM | V11: Bill To | W11: PE000820001B | X11: IMPORTACIONES RUBI S.A. | Y11: Model | Z11: WT17BV6.ABMGLGP | AA11: DFT | AB11: W/M | AC11: AMT | AD11: 166.12 | AE11: 40 | AF11: 6644.8 | AJ11: WT17BV6.ABMGLGP | AK11: Model | AL11: 0 | AM11: 0 | AN11: 0 | AQ11: 1449_8__ | AR11: 1449 | AS11: 8 | AU11: 0 | AV11: N | AW11: N

Sheet CLIENTE
A1: Fecha Inicio | B1: Fecha Fin | C1: artcod | D1: artnom | E1: artuni | F1: artlin | G1: artmar | H1: limsto | I1: limven | J1: mirsto | K1: mirven | L1: smisto | M1: smiven | N1: indsto | O1: indven | P1: punsto | Q1: linsto | R1: calst1 | S1: calst2
A2: 45411.701 | B2: 45411.701 | H2: 0 | I2: 0 | J2: 0 | K2: 0 | L2: 0 | M2: 0 | N2: 0 | O2: 0 | P2: 0 | Q2: 0 | R2: 0 | S2: 0

Sheet TP
B2: ⁬Basis Day-YYYYMMDD | C2: ⁬from Currency Code | D2: ⁬to Currency Code | E2: ⁬Xrate Type Code | F2: ⁬Xrate Type Name | G2: ⁬Exchange Rate
B3: 20240403 | C3: USD | D3: PEN | E3: 1580 | F3: LGEPR_TTM | G3: 3.711
B4: 20240404 | C4: USD | D4: PEN | E4: 1580 | F4: LGEPR_TTM | G4: 3.694
B5: 20240405 | C5: USD | D5: PEN | E5: 1580 | F5: LGEPR_TTM | G5: 3.685
B6: 20240406 | C6: USD | D6: PEN | E6: 1580 | F6: LGEPR_TTM | G6: 3.691
B7: 20240407 | C7: USD | D7: PEN | E7: 1580 | F7: LGEPR_TTM | G7: 3.691
B8: 20240408 | C8: USD | D8: PEN | E8: 1580 | F8: LGEPR_TTM | G8: 3.691
B9: 20240409 | C9: USD | D9: PEN | E9: 1580 | F9: LGEPR_TTM | G9: 3.681
B10: 20240410 | C10: USD | D10: PEN | E10: 1580 | F10: LGEPR_TTM | G10: 3.693
B11: 20240411 | C11: USD | D11: PEN | E11: 1580 | F11: LGEPR_TTM | G11: 3.71
B12: 20240412 | C12: USD | D12: PEN | E12: 1580 | F12: LGEPR_TTM | G12: 3.711
B13: 20240413 | C13: USD | D13: PEN | E13: 1580 | F13: LGEPR_TTM | G13: 3.707
B14: 20240414 | C14: USD | D14: PEN | E14: 1580 | F14: LGEPR_TTM | G14: 3.707
... B30: 20240430 | C30: USD | D30: PEN | E30: 1580 | F30: LGEPR_TTM | G30: 0

Sheet CORREO
